[{"pn":"Mr Tomas Gvazdauskas","pt":"i","n":"Tg  Autodoc Ltd","no":"SC779196","t":"Inverness","i":"automotive","in":"Car Sales & Automotive","r":"scotland","rn":"Scotland"},{"pn":"Demetre Gvasalia","pt":"i","n":"Demetre Studio Ltd","no":"16409869","t":"Leicester","i":"beauty","in":"Hair & Beauty","r":"east-midlands","rn":"East Midlands"},{"pn":"Mr Erikas Gvazdinskas","pt":"i","n":"Ernis Ltd","no":"16574928","t":"Ipswich","i":"building-services","in":"Building Services","r":"east-england","rn":"East of England"},{"pn":"Mr Petar Gvozdev","pt":"i","n":"Pitbuild Ltd","no":"08273464","t":"Romford","i":"building-services","in":"Building Services","r":"london","rn":"London"},{"pn":"Ms Tamar Gvalia","pt":"i","n":"Gs Geo Limited","no":"13206721","t":"Harrow","i":"building-services","in":"Building Services","r":"london","rn":"London"},{"pn":"Mr Martinas Gvazdikas","pt":"i","n":"Mga Fire Protection Ltd","no":"11577656","t":"London","i":"construction","in":"Construction","r":"london","rn":"London"},{"pn":"Mr Nikoloz Gvelesiani","pt":"i","n":"Niko One Limited","no":"12102451","t":"Feltham","i":"construction","in":"Construction","r":"london","rn":"London"},{"pn":"Mrs Jurgita Gvazdauskiene","pt":"i","n":"Ruby House Ltd","no":"SC856056","t":"Elgin","i":"construction","in":"Construction","r":"scotland","rn":"Scotland"},{"pn":"Mr Stefan Gvozdic","pt":"i","n":"Lsos Ltd","no":"16105123","t":"London","i":"ecommerce","in":"Online Retail & E-commerce","r":"london","rn":"London"},{"pn":"Mr Vakaris Gvazdauskas","pt":"i","n":"Totalife Ltd","no":"SC864353","t":"Inverness","i":"ecommerce","in":"Online Retail & E-commerce","r":"scotland","rn":"Scotland"},{"pn":"Natela Gvindzhiliya","pt":"i","n":"Lovat Compliance Ltd","no":"SC542008","t":"Edinburgh","i":"ecommerce","in":"Online Retail & E-commerce","r":"scotland","rn":"Scotland"},{"pn":"Mrs Nana Gvazava","pt":"i","n":"Family Gp Services Ltd","no":"14291057","t":"Brentwood","i":"healthcare","in":"Healthcare Services","r":"east-england","rn":"East of England"},{"pn":"Dr Lasha Gvinianidze","pt":"i","n":"Sylash Ltd","no":"14239994","t":"London","i":"healthcare","in":"Healthcare Services","r":"london","rn":"London"},{"pn":"Mr Mikheil Gvilia","pt":"i","n":"Vpn Marketplace Ltd","no":"14276253","t":"Cardiff","i":"it-consulting","in":"IT Consulting","r":"wales","rn":"Wales"},{"pn":"Mrs Sabina Korosec Gvozdenovic","pt":"i","n":"Bi4 Dynamics Uk Limited","no":"08043581","t":"Chesterfield","i":"it-consulting","in":"IT Consulting","r":"yorkshire","rn":"Yorkshire & Humber"},{"pn":"Mr Srdan Gvozdenovic","pt":"i","n":"Aribu Ltd","no":"14974854","t":"London","i":"management-consulting","in":"Management Consultancy","r":"london","rn":"London"},{"pn":"Mr Vladimer Gvilia","pt":"i","n":"Fortaleza Intergroup Ltd","no":"12571423","t":"Birmingham","i":"management-consulting","in":"Management Consultancy","r":"west-midlands","rn":"West Midlands"},{"pn":"Petar Gvero","pt":"i","n":"Salesinnovator Ltd","no":"16793050","t":"Manchester","i":"marketing","in":"Marketing & Advertising","r":"north-west","rn":"North West England"},{"pn":"Mr Asim Güvendik","pt":"i","n":"Anglearc Ltd","no":"14766571","t":"Tunbridge Wells","i":"marketing","in":"Marketing & Advertising","r":"south-east","rn":"South East England"},{"pn":"Mr Sergo Gvelesiani","pt":"i","n":"Sg Building & Heating Ltd","no":"10597997","t":"London","i":"plumbing","in":"Plumbing & Heating","r":"london","rn":"London"},{"pn":"Ekaterina Gvozdeva","pt":"i","n":"Aithentic Ltd","no":"16254144","t":"London","i":"pr","in":"PR & Communications","r":"london","rn":"London"},{"pn":"Mr Natan David Gvirz","pt":"i","n":"Assets And Investments Ltd","no":"16611545","t":"London","i":"property","in":"Property & Real Estate","r":"london","rn":"London"},{"pn":"Mr Alex Gvozdenovic","pt":"i","n":"Amj1 Holdings Limited","no":"09919739","t":"Sutton","i":"property","in":"Property & Real Estate","r":"london","rn":"London"},{"pn":"Dr Jasna Gvozdenovic","pt":"i","n":"Amj1 Holdings Limited","no":"09919739","t":"Sutton","i":"property","in":"Property & Real Estate","r":"london","rn":"London"},{"pn":"Mrs Jurgita Gvazdauskiene","pt":"i","n":"Jtg Properties Ltd","no":"SC771795","t":"Inverness","i":"property","in":"Property & Real Estate","r":"scotland","rn":"Scotland"},{"pn":"Mr Lasha Gvelesiani","pt":"i","n":"Glli Ltd","no":"15597312","t":"London","i":"restaurants","in":"Restaurants & Cafes","r":"london","rn":"London"},{"pn":"Mr Lasha Gvelesiani","pt":"i","n":"Gbge Limited","no":"13283689","t":"London","i":"restaurants","in":"Restaurants & Cafes","r":"london","rn":"London"},{"pn":"Mr Teimuraz Gvasalia","pt":"i","n":"Chixys Chicken Limited","no":"11417321","t":"Hayes","i":"restaurants","in":"Restaurants & Cafes","r":"london","rn":"London"},{"pn":"Mr Rustam Gvardiya","pt":"i","n":"Niya Ltd","no":"16633695","t":"London","i":"retail","in":"General Retail","r":"london","rn":"London"},{"pn":"Mr Sergey Gvardeitsev","pt":"i","n":"Itransition Software Limited","no":"07649949","t":"London","i":"software","in":"Software Development","r":"london","rn":"London"},{"pn":"Mr Sergey Gvardeitsev","pt":"i","n":"Itransition Group Limited","no":"05915098","t":"London","i":"software","in":"Software Development","r":"london","rn":"London"},{"pn":"Mr Sergey Gvardeitsev","pt":"i","n":"Itransition Holdco Limited","no":"14635749","t":"London","i":"software","in":"Software Development","r":"london","rn":"London"},{"pn":"Mr Aivaras Gvildys","pt":"i","n":"Ag Construction Group Ltd","no":"16110439","t":"March","i":"transport","in":"Road Transport & Haulage","r":"east-midlands","rn":"East Midlands"},{"pn":"Mr Jevgenij Gvozdov","pt":"i","n":"Zaev Ltd","no":"11099472","t":"Wednesbury","i":"transport","in":"Road Transport & Haulage","r":"west-midlands","rn":"West Midlands"},{"pn":"Mr Tomas Gvazdauskas","pt":"i","n":"Rover Rentals Ltd","no":"SC832074","t":"Inverness","i":"vehicle-hire","in":"Vehicle Hire & Leasing","r":"scotland","rn":"Scotland"},{"pn":"Mr Teimuraz Gvasalia","pt":"i","n":"Samma Hayes Limited","no":"12024885","t":"London","i":"wholesale","in":"Wholesale & Distribution","r":"london","rn":"London"}]