[{"pn":"Mr Uchenna Kingsley Nnadi","pt":"i","n":"Elris Konsult Ltd","no":"16199695","t":"Sunderland","i":"accommodation","in":"Guesthouses & B&Bs","r":"north-east","rn":"North East England"},{"pn":"Mr Raphael Eze Nnam","pt":"i","n":"Nnam Property Holdings Ltd","no":"16835815","t":"Swansea","i":"accommodation","in":"Guesthouses & B&Bs","r":"wales","rn":"Wales"},{"pn":"Ms Anzelika Nnadi","pt":"i","n":"Accounting Techniq Limited","no":"14787447","t":"Wickford","i":"accounting","in":"Accounting & Bookkeeping","r":"east-england","rn":"East of England"},{"pn":"Mr Kelechi Nnawuchi","pt":"i","n":"Kcn Business Limited","no":"09882235","t":"Ebbsfleet","i":"accounting","in":"Accounting & Bookkeeping","r":"london","rn":"London"},{"pn":"Ms Maureen Chioma Nnamani","pt":"i","n":"Mcn Accountants Ltd","no":"12593586","t":"Potters Bar","i":"accounting","in":"Accounting & Bookkeeping","r":"london","rn":"London"},{"pn":"Mrs Maureen Chioma Nnamani","pt":"i","n":"Mcn Accountants Ltd","no":"12593586","t":"Potters Bar","i":"accounting","in":"Accounting & Bookkeeping","r":"london","rn":"London"},{"pn":"Miss Maureen Chioma Nnamani","pt":"i","n":"Mcn Accountants Ltd","no":"12593586","t":"Potters Bar","i":"accounting","in":"Accounting & Bookkeeping","r":"london","rn":"London"},{"pn":"Uchenna Chioma Nnabuko","pt":"i","n":"Gquavers Studio Limited","no":"SC664114","t":"Edinburgh","i":"arts","in":"Arts & Entertainment","r":"scotland","rn":"Scotland"},{"pn":"Mr Stanley Chinonso Nnabugwu","pt":"i","n":"S&G Auto Bros Ltd","no":"SC861554","t":"Aberdeen","i":"automotive","in":"Car Sales & Automotive","r":"scotland","rn":"Scotland"},{"pn":"Franklyn Nnamdi-Okwedy","pt":"i","n":"F4Fade Ltd","no":"13098824","t":"London","i":"beauty","in":"Hair & Beauty","r":"london","rn":"London"},{"pn":"Mr Francis Nnabueze","pt":"i","n":"Nice Cut Limited","no":"06492603","t":"London","i":"beauty","in":"Hair & Beauty","r":"london","rn":"London"},{"pn":"Ms Lyna Nneka","pt":"i","n":"Veelocks Uk Ltd","no":"12342170","t":"London","i":"beauty","in":"Hair & Beauty","r":"london","rn":"London"},{"pn":"Mrs Yvonne Obioma Nnaji","pt":"i","n":"Ivonmelda Ltd","no":"15576551","t":"Salford","i":"beauty","in":"Hair & Beauty","r":"north-west","rn":"North West England"},{"pn":"Mrs Yvonne Obioma Nnaji","pt":"i","n":"Ivonmeldabynwanne Ltd","no":"16392966","t":"Salford","i":"beauty","in":"Hair & Beauty","r":"north-west","rn":"North West England"},{"pn":"Ujunwa Emmanuela Nnebuo","pt":"i","n":"Ellagills Touch Ltd","no":"17018626","t":"Barrow-In-Furness","i":"beauty","in":"Hair & Beauty","r":"north-west","rn":"North West England"},{"pn":"Mr Obinna Emmanuel Nnaemeka","pt":"i","n":"Precision Intents Ltd","no":"SC869952","t":"Glasgow","i":"beauty","in":"Hair & Beauty","r":"scotland","rn":"Scotland"},{"pn":"Miss Uchenna Raluchukwu Shanty Nnanwubar","pt":"i","n":"Aesthetics By Shanty Limited","no":"16364178","t":"Maidenhead","i":"beauty","in":"Hair & Beauty","r":"south-east","rn":"South East England"},{"pn":"Mrs Lovette Ifunanya Nnamoko-Anejo","pt":"i","n":"L & P Apartments Limited","no":"15639129","t":"Suffolk","i":"building-services","in":"Building Services","r":"east-england","rn":"East of England"},{"pn":"Mr Charles Ndumim Nnah","pt":"i","n":"Charliemoore Solutions Ltd","no":"14809482","t":"Croydon","i":"building-services","in":"Building Services","r":"london","rn":"London"},{"pn":"Mr Nathan Maduabuchi Nnadi","pt":"i","n":"Nat Fix Limited","no":"11184555","t":"Gravesend","i":"building-services","in":"Building Services","r":"london","rn":"London"},{"pn":"Mr Emmanuel Ifeanyi Nnaji","pt":"i","n":"Prudents Drylinig Solutions Limited","no":"16258172","t":"Manchester","i":"building-services","in":"Building Services","r":"north-west","rn":"North West England"},{"pn":"Mrs Viviane Ngomo Nnegue","pt":"i","n":"Richvive Ltd","no":"07408011","t":"Northampton","i":"catering","in":"Event Catering","r":"east-midlands","rn":"East Midlands"},{"pn":"Ms Doree Louise-Marie Lukama Mkakomba Nnaweza","pt":"i","n":"Steam Foods Ltd","no":"14207062","t":"London","i":"catering","in":"Event Catering","r":"london","rn":"London"},{"pn":"Mr Richard Chinedu Nnadi","pt":"i","n":"Jjb Food Concepts Uk Ltd","no":"14950981","t":"London","i":"catering","in":"Event Catering","r":"london","rn":"London"},{"pn":"Mr Richard Chinedu Nnadi","pt":"i","n":"Wexford Global Ltd","no":"16657203","t":"London","i":"catering","in":"Event Catering","r":"london","rn":"London"},{"pn":"Miss Chinenye Nnabude","pt":"i","n":"The Senora Co Limited","no":"16763779","t":"Purley","i":"catering","in":"Event Catering","r":"london","rn":"London"},{"pn":"Mr Richard Chinedu Nnadi","pt":"i","n":"Eve After Dark Food Concepts Uk Ltd","no":"14082017","t":"London","i":"catering","in":"Event Catering","r":"london","rn":"London"},{"pn":"Mrs Chinomso Jenifa Nnaemeka-Jude","pt":"i","n":"Lights&Miracles Limited","no":"16337066","t":"Manchester","i":"catering","in":"Event Catering","r":"north-west","rn":"North West England"},{"pn":"Mrs Lucia Onyinye Nnamani","pt":"i","n":"042 Ng Kitchen Uk Limited","no":"16306154","t":"Leeds","i":"catering","in":"Event Catering","r":"yorkshire","rn":"Yorkshire & Humber"},{"pn":"Dr Ace Nnorom","pt":"i","n":"Cuddly Arms Daycare Nursery Limited","no":"10926982","t":"Stockport","i":"childcare","in":"Childcare & Day Nurseries","r":"north-west","rn":"North West England"},{"pn":"Mr Henry Nnabuenyi","pt":"i","n":"Cheeky Nursery Ltd","no":"12179751","t":"Cardiff","i":"childcare","in":"Childcare & Day Nurseries","r":"wales","rn":"Wales"},{"pn":"Mrs Gloria Uruaku Nnamdi","pt":"i","n":"Facilitycare Solutions Ltd","no":"16790045","t":"Basildon","i":"cleaning","in":"Commercial Cleaning","r":"east-england","rn":"East of England"},{"pn":"Mr Patrick Chigekwu Nnebedum","pt":"i","n":"Strides Housekeeping Services Ltd","no":"15480337","t":"Enfield","i":"cleaning","in":"Commercial Cleaning","r":"london","rn":"London"},{"pn":"Mr Ikechukwu Christopher Nnalue","pt":"i","n":"Wyte Oak Ltd","no":"16233088","t":"London","i":"cleaning","in":"Commercial Cleaning","r":"london","rn":"London"},{"pn":"Mr Ikechukwu Nelson Nnabuihe","pt":"i","n":"Alphaluxe Cleaners Ltd","no":"16531450","t":"Manchester","i":"cleaning","in":"Commercial Cleaning","r":"north-west","rn":"North West England"},{"pn":"Miss Eudora Nnadi","pt":"i","n":"Just Clean And Moving Service Limited","no":"16229362","t":"Manchester","i":"cleaning","in":"Commercial Cleaning","r":"north-west","rn":"North West England"},{"pn":"Mr Bob Izuchukwu Nnanna","pt":"i","n":"Clean And Sparkle Cleaning Limited","no":"11002901","t":"Cardiff","i":"cleaning","in":"Commercial Cleaning","r":"wales","rn":"Wales"},{"pn":"Mr Chukwudube Raphael Nnabuife","pt":"i","n":"The Pristine Team Ltd","no":"16233022","t":"Birmingham","i":"cleaning","in":"Commercial Cleaning","r":"west-midlands","rn":"West Midlands"},{"pn":"Augustine Okoro Nnabugwu","pt":"i","n":"Nesipart Ventures Ltd","no":"10499789","t":"London","i":"construction","in":"Construction","r":"london","rn":"London"},{"pn":"Ms Evelyn Nneji","pt":"i","n":"Shawshelaly Ltd","no":"10251916","t":"London","i":"construction","in":"Construction","r":"london","rn":"London"},{"pn":"Mr Frank Okechukwu Nnadi","pt":"i","n":"Frankbest Construction Ltd","no":"14871431","t":"Barking","i":"construction","in":"Construction","r":"london","rn":"London"},{"pn":"Mr Iheanacho Anthony Nnodi","pt":"i","n":"Nnodi Group Limited","no":"15950187","t":"London","i":"construction","in":"Construction","r":"london","rn":"London"},{"pn":"Amanze Alphonsus Nnadi","pt":"i","n":"Mazon Global Limited","no":"16401355","t":"Sunderland","i":"construction","in":"Construction","r":"north-east","rn":"North East England"},{"pn":"Mr Peter Ikechukwu Nnamani","pt":"i","n":"Petersedge Limited","no":"16810033","t":"Chatham","i":"construction","in":"Construction","r":"south-east","rn":"South East England"},{"pn":"Mr. Nnamdi Patrick Nnatu","pt":"i","n":"Pat-At-Hand Construction Services Ltd","no":"16736164","t":"Birmingham","i":"construction","in":"Construction","r":"west-midlands","rn":"West Midlands"},{"pn":"Chinwe Alexandra Nnadi","pt":"i","n":"Zion Talent Capital Ltd","no":"14044978","t":"Brentwood","i":"consultancy","in":"Business Consultancy","r":"east-england","rn":"East of England"},{"pn":"Ms Uchechukwu Nnene","pt":"i","n":"Effectivepoint Limited","no":"03637195","t":"Edmonton","i":"consultancy","in":"Business Consultancy","r":"london","rn":"London"},{"pn":"Mr Osinachi Chinonso Nnabuko","pt":"i","n":"Softchem Limited","no":"SC503086","t":"Aberdeen","i":"consultancy","in":"Business Consultancy","r":"scotland","rn":"Scotland"},{"pn":"Mr Ndukwu Nnamdi","pt":"i","n":"Zamias Limited","no":"12097575","t":"Cardiff","i":"consultancy","in":"Business Consultancy","r":"wales","rn":"Wales"},{"pn":"Mrs. Chidinma Judith Nnamdi","pt":"i","n":"1 Goal Analytics Limited","no":"15531019","t":"London","i":"data-services","in":"Data Processing & Hosting","r":"london","rn":"London"},{"pn":"Mrs Ngozi Happiness Nneke","pt":"i","n":"Next Medics Ltd","no":"16487624","t":"Sale","i":"data-services","in":"Data Processing & Hosting","r":"north-west","rn":"North West England"},{"pn":"Chiagoziem John Nneke","pt":"i","n":"Next Medics Ltd","no":"16487624","t":"Sale","i":"data-services","in":"Data Processing & Hosting","r":"north-west","rn":"North West England"},{"pn":"Vivian Uloma Nnaduogu","pt":"i","n":"Vivichi Concept Ltd","no":"SC860141","t":"Paisley","i":"data-services","in":"Data Processing & Hosting","r":"scotland","rn":"Scotland"},{"pn":"Mrs Patricia Obioma Nnadozie","pt":"i","n":"Auricleaf Limited","no":"16282074","t":"Bury St. Edmunds","i":"ecommerce","in":"Online Retail & E-commerce","r":"east-england","rn":"East of England"},{"pn":"Mr Charles Nnanyelugo","pt":"i","n":"Donventures Ltd","no":"14371591","t":"Harlow","i":"ecommerce","in":"Online Retail & E-commerce","r":"east-england","rn":"East of England"},{"pn":"Dr Nkiruka Nnabuife","pt":"i","n":"More Than Culture Ltd","no":"16189893","t":"Bury St. Edmunds","i":"ecommerce","in":"Online Retail & E-commerce","r":"east-england","rn":"East of England"},{"pn":"Mr Dozie Nnabuife","pt":"i","n":"More Than Culture Ltd","no":"16189893","t":"Bury St. Edmunds","i":"ecommerce","in":"Online Retail & E-commerce","r":"east-england","rn":"East of England"},{"pn":"Mrs Jane Nnawowo","pt":"i","n":"Becoming A Woman Cic","no":"15400495","t":"Bury St. Edmunds","i":"ecommerce","in":"Online Retail & E-commerce","r":"east-england","rn":"East of England"},{"pn":"Mr Paul James Nnaemeka","pt":"i","n":"Tca Global Ltd","no":"15901653","t":"Coventry","i":"ecommerce","in":"Online Retail & E-commerce","r":"east-midlands","rn":"East Midlands"},{"pn":"Mrs Chidinma Nnaemeka","pt":"i","n":"Tca Global Ltd","no":"15901653","t":"Coventry","i":"ecommerce","in":"Online Retail & E-commerce","r":"east-midlands","rn":"East Midlands"},{"pn":"Mrs Esther Ifeoma Nnamdi","pt":"i","n":"Mums Heritage Limited","no":"16566945","t":"Bedford","i":"ecommerce","in":"Online Retail & E-commerce","r":"east-midlands","rn":"East Midlands"},{"pn":"Mr Chukwuemeka Nnamdi George Nnadi","pt":"i","n":"Vollertech Ltd","no":"16349870","t":"London","i":"ecommerce","in":"Online Retail & E-commerce","r":"london","rn":"London"},{"pn":"Mr Joseph Obinna Nnodim","pt":"i","n":"Lock In Store Limited","no":"13874860","t":"Ilford","i":"ecommerce","in":"Online Retail & E-commerce","r":"london","rn":"London"},{"pn":"Mr Echezonachukwu Anthony Nnamani","pt":"i","n":"Vidi Beauty Ltd","no":"17052867","t":"London","i":"ecommerce","in":"Online Retail & E-commerce","r":"london","rn":"London"},{"pn":"Chijioke Richard Nneji","pt":"i","n":"Richlinks Ltd","no":"15851473","t":"London","i":"ecommerce","in":"Online Retail & E-commerce","r":"london","rn":"London"},{"pn":"Mrs Eniola Tanitoluwa Nnani","pt":"i","n":"Cladini Studio Ltd","no":"16522015","t":"Watford","i":"ecommerce","in":"Online Retail & E-commerce","r":"london","rn":"London"},{"pn":"Mr Petrus Nnolim","pt":"i","n":"Petno Group Limited","no":"15353064","t":"London","i":"ecommerce","in":"Online Retail & E-commerce","r":"london","rn":"London"},{"pn":"Ifeyinwa Jane Nnadi","pt":"i","n":"Jpl Global Ltd","no":"15956647","t":"Belvedere","i":"ecommerce","in":"Online Retail & E-commerce","r":"london","rn":"London"},{"pn":"Christian Emeka Nnabugwu","pt":"i","n":"Medsun Ltd","no":"16503315","t":"Croydon","i":"ecommerce","in":"Online Retail & E-commerce","r":"london","rn":"London"},{"pn":"Mr Chidozie Nnadi","pt":"i","n":"Noace Ltd","no":"13121195","t":"London","i":"ecommerce","in":"Online Retail & E-commerce","r":"london","rn":"London"},{"pn":"Miss Krystle Kenechukwu Nnadi","pt":"i","n":"Krys Luxe Beauty Ltd","no":"13119243","t":"London","i":"ecommerce","in":"Online Retail & E-commerce","r":"london","rn":"London"},{"pn":"Miss Kelechi Vivian Nnamdi-Maxwell","pt":"i","n":"El'VeelaãN Uk Ltd","no":"12931080","t":"London","i":"ecommerce","in":"Online Retail & E-commerce","r":"london","rn":"London"},{"pn":"Mrs Ekwutosi Nnene","pt":"i","n":"Equi Botanics Limited","no":"10160045","t":"London","i":"ecommerce","in":"Online Retail & E-commerce","r":"london","rn":"London"},{"pn":"Mrs Nneoma Nnorom","pt":"i","n":"Taleforward Ltd","no":"16886993","t":"London","i":"ecommerce","in":"Online Retail & E-commerce","r":"london","rn":"London"},{"pn":"Ms Jennifer Ijeoma Nnakaihe","pt":"i","n":"Nedora Bloom Ltd","no":"16939534","t":"London","i":"ecommerce","in":"Online Retail & E-commerce","r":"london","rn":"London"},{"pn":"Matthew Chigozie Nnadozie","pt":"i","n":"Madoxy Group Limited","no":"16998776","t":"Wallsend","i":"ecommerce","in":"Online Retail & E-commerce","r":"north-east","rn":"North East England"},{"pn":"Mr Johnkennedy Chinazaepkere Nnanyere","pt":"i","n":"Eu&Charis Limited","no":"16056924","t":"Seaham","i":"ecommerce","in":"Online Retail & E-commerce","r":"north-east","rn":"North East England"},{"pn":"Mr Kelvin Uchenna Nnabude","pt":"i","n":"Boldston Group Ltd","no":"11740894","t":"Manchester","i":"ecommerce","in":"Online Retail & E-commerce","r":"north-west","rn":"North West England"},{"pn":"Mr Chima Gibson Nnadiekwe","pt":"i","n":"K.Klassic Global Ltd","no":"SC859884","t":"Ayr","i":"ecommerce","in":"Online Retail & E-commerce","r":"scotland","rn":"Scotland"},{"pn":"Ms Josephine Nkeonye-Aswa Nnamdiegwu","pt":"i","n":"The Sephin Group Ltd","no":"SC878746","t":"Glasgow","i":"ecommerce","in":"Online Retail & E-commerce","r":"scotland","rn":"Scotland"},{"pn":"Chukwudi Batholomew Nnaji","pt":"i","n":"Nelly Chucks Apparel Ltd","no":"13770380","t":"Chatham","i":"ecommerce","in":"Online Retail & E-commerce","r":"south-east","rn":"South East England"},{"pn":"Ugochukwu Uzoma Nnodi","pt":"i","n":"Ecothrived Solutions Ltd","no":"16768002","t":"Rochester","i":"ecommerce","in":"Online Retail & E-commerce","r":"south-east","rn":"South East England"},{"pn":"Miss Chimnwenmmeri Esther Nnadi","pt":"i","n":"Chinat Limited","no":"16111506","t":"Nottinghamshire.","i":"ecommerce","in":"Online Retail & E-commerce","r":"yorkshire","rn":"Yorkshire & Humber"},{"pn":"Mr Kingsley Ebubechukwu Nnakenyi","pt":"i","n":"Control6Smarthomes Ltd","no":"15039553","t":"Esher","i":"electrical","in":"Electrical Services","r":"london","rn":"London"},{"pn":"Mr Fine Baruch Nnaji","pt":"i","n":"Noble Support Services Ltd","no":"12292809","t":"Hatfield","i":"healthcare","in":"Healthcare Services","r":"east-england","rn":"East of England"},{"pn":"Mr Samuel Okechukwu Nnadi","pt":"i","n":"Liteplate Enterprise Limited","no":"15966496","t":"Luton","i":"healthcare","in":"Healthcare Services","r":"east-england","rn":"East of England"},{"pn":"Mrs Preciousnorah Olachi Nnadi","pt":"i","n":"Liteplate Enterprise Limited","no":"15966496","t":"Luton","i":"healthcare","in":"Healthcare Services","r":"east-england","rn":"East of England"},{"pn":"Mrs Edith Nnalue","pt":"i","n":"Dreamlight Healthcare Ltd","no":"09596212","t":"St Albans","i":"healthcare","in":"Healthcare Services","r":"east-england","rn":"East of England"},{"pn":"Dr Philip Goliba Nnadozie","pt":"i","n":"Shogaz Limited","no":"13563004","t":"Harlow","i":"healthcare","in":"Healthcare Services","r":"east-england","rn":"East of England"},{"pn":"Mrs Folashade Benedicta Nnadozie","pt":"i","n":"Shogaz Limited","no":"13563004","t":"Harlow","i":"healthcare","in":"Healthcare Services","r":"east-england","rn":"East of England"},{"pn":"Amaoge Euphemia Nnabuchi","pt":"i","n":"Osinachi And Chiamaka Ltd","no":"15946894","t":"Essex","i":"healthcare","in":"Healthcare Services","r":"east-england","rn":"East of England"},{"pn":"Daniel Chukwuchebe Nneji","pt":"i","n":"Dannymore Limited","no":"11041889","t":"Harlow","i":"healthcare","in":"Healthcare Services","r":"east-england","rn":"East of England"},{"pn":"Adaku Chinwe Nnoli","pt":"i","n":"Acn Health Limited","no":"16756491","t":"Harlow","i":"healthcare","in":"Healthcare Services","r":"east-england","rn":"East of England"},{"pn":"Mrs Christine Nnadi","pt":"i","n":"Ijada Health Care Limited","no":"11334008","t":"Peterborough","i":"healthcare","in":"Healthcare Services","r":"east-midlands","rn":"East Midlands"},{"pn":"Dr Ian Okechukwu Nnatu","pt":"i","n":"Nnatu Consulting Ltd","no":"14123151","t":"Lincoln","i":"healthcare","in":"Healthcare Services","r":"east-midlands","rn":"East Midlands"},{"pn":"Mrs Patricia Obioma Nnadozie","pt":"i","n":"Patclems Ltd","no":"13408004","t":"Northampton","i":"healthcare","in":"Healthcare Services","r":"east-midlands","rn":"East Midlands"},{"pn":"Mr Valentine Nnadi","pt":"i","n":"Turkvin Global Limited","no":"13961684","t":"Hinckley","i":"healthcare","in":"Healthcare Services","r":"east-midlands","rn":"East Midlands"},{"pn":"Mr Godwin Arinze Nnoka","pt":"i","n":"Starinze Ltd","no":"14641443","t":"Wellingborough","i":"healthcare","in":"Healthcare Services","r":"east-midlands","rn":"East Midlands"},{"pn":"Mr Henry Obinna Nnajiuba","pt":"i","n":"Kai Kai Limited","no":"09711110","t":"Grays","i":"healthcare","in":"Healthcare Services","r":"london","rn":"London"},{"pn":"Mrs Immaculata Nnadi","pt":"i","n":"Tubapi Ltd","no":"08379061","t":"Dagenham","i":"healthcare","in":"Healthcare Services","r":"london","rn":"London"},{"pn":"Ms Esther Chiemeka Nnadi","pt":"i","n":"Jc-Lovann Ltd","no":"14898628","t":"Bromley","i":"healthcare","in":"Healthcare Services","r":"london","rn":"London"},{"pn":"Phyllis Chinyere Nnadi","pt":"i","n":"Jup Medicals Limited","no":"08309327","t":"London","i":"healthcare","in":"Healthcare Services","r":"london","rn":"London"},{"pn":"Mr Julian Nnadi","pt":"i","n":"Jup Medicals Limited","no":"08309327","t":"London","i":"healthcare","in":"Healthcare Services","r":"london","rn":"London"},{"pn":"Ms Ursula Uzoamaka Nnadi","pt":"i","n":"Unficient Limited","no":"15681406","t":"London","i":"healthcare","in":"Healthcare Services","r":"london","rn":"London"},{"pn":"Miss Nancy Nneoma Nnodi","pt":"i","n":"Nanah Ivy Limited","no":"16541820","t":"Harrow","i":"healthcare","in":"Healthcare Services","r":"london","rn":"London"},{"pn":"Miss Esther Nadia Nnoumoulolo","pt":"i","n":"Jf Care With Love Ltd","no":"15229643","t":"London","i":"healthcare","in":"Healthcare Services","r":"london","rn":"London"},{"pn":"Mrs Rosemary Nnadi","pt":"i","n":"Alphabeta Services Limited","no":"13218514","t":"Waltham Cross","i":"healthcare","in":"Healthcare Services","r":"london","rn":"London"},{"pn":"Ms Olubanke Olufolake Nnebedum","pt":"i","n":"Barrj'S Global Consulting Ltd","no":"16194781","t":"Enfield","i":"healthcare","in":"Healthcare Services","r":"london","rn":"London"},{"pn":"Mrs Sarra Nneoma","pt":"i","n":"Ovuike Healthcare Ltd","no":"05338195","t":"Romford","i":"healthcare","in":"Healthcare Services","r":"london","rn":"London"},{"pn":"Ijeoma Nnorom","pt":"i","n":"Hadas Health U.K Ltd","no":"16327230","t":"London","i":"healthcare","in":"Healthcare Services","r":"london","rn":"London"},{"pn":"Patience Nnamdi-Nwaefulu","pt":"i","n":"Oasis Space Therapy Ltd","no":"15423432","t":"Edgware","i":"healthcare","in":"Healthcare Services","r":"london","rn":"London"},{"pn":"Dr Guy Emeka Nnanwubar","pt":"i","n":"Mykami Synergies Ltd","no":"14601243","t":"London","i":"healthcare","in":"Healthcare Services","r":"london","rn":"London"},{"pn":"Ms Belle Nnorom","pt":"i","n":"Belux Wellness Ltd","no":"17035156","t":"Croydon","i":"healthcare","in":"Healthcare Services","r":"london","rn":"London"},{"pn":"Dr Andrew Onyema Nnadi","pt":"i","n":"Lasaderm Treatments Limited","no":"13334814","t":"Borehamwood","i":"healthcare","in":"Healthcare Services","r":"london","rn":"London"},{"pn":"Onyekachi Okenwa Nnam","pt":"i","n":"Csinkocool Limited","no":"14046460","t":"Hayes","i":"healthcare","in":"Healthcare Services","r":"london","rn":"London"},{"pn":"Mrs Chika Julian Obioha Nnadika","pt":"i","n":"Chijulian Pharmaceutical International Limited","no":"14861898","t":"London","i":"healthcare","in":"Healthcare Services","r":"london","rn":"London"},{"pn":"Dr Akobundu Nnochini","pt":"i","n":"Women'S Gynaechoice Ltd","no":"05282840","t":"London","i":"healthcare","in":"Healthcare Services","r":"london","rn":"London"},{"pn":"Mrs Stella Oluchi Nnawugo","pt":"i","n":"Stella Healthcare Limited","no":"09432630","t":"Morden","i":"healthcare","in":"Healthcare Services","r":"london","rn":"London"},{"pn":"Mr Emmanuel Chukwuemeka Nnadi","pt":"i","n":"Simid Consultancy Limited","no":"13791033","t":"Barking","i":"healthcare","in":"Healthcare Services","r":"london","rn":"London"},{"pn":"Mrs Sylvia Ozichi Nnadi","pt":"i","n":"Simid Consultancy Limited","no":"13791033","t":"Barking","i":"healthcare","in":"Healthcare Services","r":"london","rn":"London"},{"pn":"Susan Nnana","pt":"i","n":"Suzy Healthcare Services Limited","no":"13556689","t":"London","i":"healthcare","in":"Healthcare Services","r":"london","rn":"London"},{"pn":"Dr Ugochi Nnaji","pt":"i","n":"Guchy Consultancy Limited","no":"14162859","t":"Royal Arsenal","i":"healthcare","in":"Healthcare Services","r":"london","rn":"London"},{"pn":"Ms Ifeoma Nnona","pt":"i","n":"Warm Hearted Healthcare Ltd","no":"14402321","t":"Barnet","i":"healthcare","in":"Healthcare Services","r":"london","rn":"London"},{"pn":"Mr Oliver Okoro Nnabugwu","pt":"i","n":"Olins Health Limited","no":"13776955","t":"London","i":"healthcare","in":"Healthcare Services","r":"london","rn":"London"},{"pn":"Dr Kenechi Nnabuchi","pt":"i","n":"Evergreen Medicals Ltd","no":"14301288","t":"Stockton-On-Tees","i":"healthcare","in":"Healthcare Services","r":"north-east","rn":"North East England"},{"pn":"Mrs Chinaza Jane Nnabuchi","pt":"i","n":"Evergreen Medicals Ltd","no":"14301288","t":"Stockton-On-Tees","i":"healthcare","in":"Healthcare Services","r":"north-east","rn":"North East England"},{"pn":"Tobechi Onyekachi Nna","pt":"i","n":"Aquila Medical Services Limited","no":"09707242","t":"Warrington","i":"healthcare","in":"Healthcare Services","r":"north-west","rn":"North West England"},{"pn":"Mr Chukwuemeka Christopher Nnamani","pt":"i","n":"Coowan Group Limited","no":"16655996","t":"Workington","i":"healthcare","in":"Healthcare Services","r":"north-west","rn":"North West England"},{"pn":"Miss Rehema Kiwanuka Nnabukeera","pt":"i","n":"Apothecaring Ltd","no":"05821675","t":"Cheshire","i":"healthcare","in":"Healthcare Services","r":"north-west","rn":"North West England"},{"pn":"Ms Anyachonkeya Lovina Nnajiobi","pt":"i","n":"Joechi Consultant Limited","no":"10010542","t":"Manchester","i":"healthcare","in":"Healthcare Services","r":"north-west","rn":"North West England"},{"pn":"Mr. Ekene Nnadozie","pt":"i","n":"Nuturwell Care Ltd","no":"15841222","t":"Bolton","i":"healthcare","in":"Healthcare Services","r":"north-west","rn":"North West England"},{"pn":"Dr John Nneke","pt":"i","n":"Savimedics Limited","no":"12450918","t":"Sale","i":"healthcare","in":"Healthcare Services","r":"north-west","rn":"North West England"},{"pn":"Mr Kenechi Fredrick Nnadi","pt":"i","n":"Fk Nnadi Ltd","no":"NI710663","t":"Belfast","i":"healthcare","in":"Healthcare Services","r":"northern-ireland","rn":"Northern Ireland"},{"pn":"Olivia Obianujuaku Nnamani","pt":"i","n":"Vialio Consulting Limited","no":"NI714728","t":"Newtownabbey","i":"healthcare","in":"Healthcare Services","r":"northern-ireland","rn":"Northern Ireland"},{"pn":"Mrs Immaculata Chinomso Nnabuko","pt":"i","n":"Aberdeenshire Homecare Services Ltd","no":"SC824169","t":"Aberdeen","i":"healthcare","in":"Healthcare Services","r":"scotland","rn":"Scotland"},{"pn":"Mr Azuka Frank Nnabue","pt":"i","n":"Connect Staffing Ltd","no":"14623425","t":"Rochester","i":"healthcare","in":"Healthcare Services","r":"south-east","rn":"South East England"},{"pn":"Mr Edward Nwannediuko Nnando","pt":"i","n":"Sana Vita Limited","no":"15296852","t":"Canterbury","i":"healthcare","in":"Healthcare Services","r":"south-east","rn":"South East England"},{"pn":"Mr Colin Nnadi","pt":"i","n":"Oxfordscoliosis Limited","no":"09319927","t":"Oxford","i":"healthcare","in":"Healthcare Services","r":"south-east","rn":"South East England"},{"pn":"Ms Chisom Nnamchi","pt":"i","n":"Chezok Limited","no":"08533924","t":"Sittingbourne","i":"healthcare","in":"Healthcare Services","r":"south-east","rn":"South East England"},{"pn":"Mr Ndubuisi Benignus Nnamdi","pt":"i","n":"P2P - Person To Person Talking Therapies Ltd","no":"12804251","t":"Wokingham","i":"healthcare","in":"Healthcare Services","r":"south-east","rn":"South East England"},{"pn":"Mr Ifeanyi Anthony Nnadozie","pt":"i","n":"Aximia Limited","no":"14282741","t":"Basingstoke","i":"healthcare","in":"Healthcare Services","r":"south-east","rn":"South East England"},{"pn":"Amaka Celestina Nnolum","pt":"i","n":"Amacel Concept Ltd","no":"14033523","t":"Maidstone","i":"healthcare","in":"Healthcare Services","r":"south-east","rn":"South East England"},{"pn":"Dr Mary Frances Nnankya","pt":"i","n":"Manov Bioteclinica Limited","no":"13604973","t":"Banbury","i":"healthcare","in":"Healthcare Services","r":"south-east","rn":"South East England"},{"pn":"Mr Stephen Onyinye Nnaka","pt":"i","n":"Lance Nursing Services Ltd","no":"12063334","t":"Bristol","i":"healthcare","in":"Healthcare Services","r":"south-west","rn":"South West England"},{"pn":"Mr Charles Ogbonna Nnamdi","pt":"i","n":"Nnamdi Healthcare Ltd","no":"12104467","t":"Bristol","i":"healthcare","in":"Healthcare Services","r":"south-west","rn":"South West England"},{"pn":"Mr Prince Onyekachi Nnaji","pt":"i","n":"Gladnnaji Limited","no":"14431665","t":"Wolverhampton","i":"healthcare","in":"Healthcare Services","r":"west-midlands","rn":"West Midlands"},{"pn":"Dr Ikechukwu Henry Nnamani","pt":"i","n":"Hik Medics Limited","no":"16854499","t":"Newcastle","i":"healthcare","in":"Healthcare Services","r":"west-midlands","rn":"West Midlands"},{"pn":"Mr Theodore Nnadiasor","pt":"i","n":"Theodore Solutions Limited","no":"15326384","t":"Wolverhampton","i":"healthcare","in":"Healthcare Services","r":"west-midlands","rn":"West Midlands"},{"pn":"Ms Ngamanya Nnorom","pt":"i","n":"Uplifting Lives Services Ltd","no":"10846305","t":"Worcestershire","i":"healthcare","in":"Healthcare Services","r":"west-midlands","rn":"West Midlands"},{"pn":"Miss Amarachi Nnochiri","pt":"i","n":"Yama Healthcare Group Ltd","no":"16886288","t":"Wolverhampton","i":"healthcare","in":"Healthcare Services","r":"west-midlands","rn":"West Midlands"},{"pn":"Ms Dorothy Chibuzo Nneji","pt":"i","n":"Pentecost Associates Limited","no":"11015194","t":"Swindon","i":"healthcare","in":"Healthcare Services","r":"yorkshire","rn":"Yorkshire & Humber"},{"pn":"Mrs Chioma Ken Nnamdi","pt":"i","n":"Nnaoma Consulting Limited","no":"13790904","t":"Doncaster","i":"healthcare","in":"Healthcare Services","r":"yorkshire","rn":"Yorkshire & Humber"},{"pn":"Miss Jade Nnamani","pt":"i","n":"Luxe K Stays Ltd","no":"15234923","t":"London","i":"hotels","in":"Hotels & Accommodation","r":"london","rn":"London"},{"pn":"Ms Cynthia Nonye Nnaji","pt":"i","n":"Fabcribs Limited","no":"14107871","t":"Grays","i":"hotels","in":"Hotels & Accommodation","r":"london","rn":"London"},{"pn":"Miss Bethany Immaculate Nnwangi","pt":"i","n":"Bevial Ltd","no":"16955782","t":"London","i":"hotels","in":"Hotels & Accommodation","r":"london","rn":"London"},{"pn":"Mr Kenneth Chidubem Nnadikwe","pt":"i","n":"Global Hybrid Technology Solutions Limited","no":"13676449","t":"Harlow","i":"it-consulting","in":"IT Consulting","r":"east-england","rn":"East of England"},{"pn":"Ms Adannaya Caroline Nnadi","pt":"i","n":"Honeywell Technologies Ltd","no":"08602510","t":"St Albans","i":"it-consulting","in":"IT Consulting","r":"east-england","rn":"East of England"},{"pn":"Dr Onyinyechukwu Nneamaka Nnadi","pt":"i","n":"Josee Consulting Ltd","no":"13994679","t":"Nuneaton","i":"it-consulting","in":"IT Consulting","r":"east-midlands","rn":"East Midlands"},{"pn":"Promise Nnaka","pt":"i","n":"Water Of Wealth Ltd","no":"17004822","t":"London","i":"it-consulting","in":"IT Consulting","r":"london","rn":"London"},{"pn":"Mr Oliver Nnona","pt":"i","n":"Incubenta Limited","no":"13538572","t":"London","i":"it-consulting","in":"IT Consulting","r":"london","rn":"London"},{"pn":"Mr Donald Nnama","pt":"i","n":"Td Sprints Ltd","no":"08306998","t":"London","i":"it-consulting","in":"IT Consulting","r":"london","rn":"London"},{"pn":"Mr Ikenna Kenneth Edwin Nnadi","pt":"i","n":"Agent Kaziori Limited","no":"16989748","t":"Bromley","i":"it-consulting","in":"IT Consulting","r":"london","rn":"London"},{"pn":"Mr Felix Ebuka Nnadozie","pt":"i","n":"London Smart Technology Company Limited","no":"11124243","t":"London","i":"it-consulting","in":"IT Consulting","r":"london","rn":"London"},{"pn":"Mr Godson Chinedum Nnawuchi","pt":"i","n":"Cnbn Ltd","no":"08905915","t":"Grays","i":"it-consulting","in":"IT Consulting","r":"london","rn":"London"},{"pn":"Mr Chinedum Nnawuchi","pt":"i","n":"Quantum Stratus Ltd","no":"15222121","t":"Grays","i":"it-consulting","in":"IT Consulting","r":"london","rn":"London"},{"pn":"Mr Benjamin Chinedu Nnamani","pt":"i","n":"Okomart Ltd","no":"12949390","t":"London","i":"it-consulting","in":"IT Consulting","r":"london","rn":"London"},{"pn":"Mr Chinedu Nnadi","pt":"i","n":"Ice And N Build Resources Ltd","no":"09036174","t":"London","i":"it-consulting","in":"IT Consulting","r":"london","rn":"London"},{"pn":"Dr Somtochukwu Godfrey Nnabuife","pt":"i","n":"Sion Group Ltd","no":"14657887","t":"London","i":"it-consulting","in":"IT Consulting","r":"london","rn":"London"},{"pn":"Mr Christian James Chimdi Nnochiri","pt":"i","n":"Chris Jammer Ltd","no":"15133827","t":"London","i":"it-consulting","in":"IT Consulting","r":"london","rn":"London"},{"pn":"Mr Joseph Obinna Nnodim","pt":"i","n":"Cyyte Limited","no":"05703806","t":"","i":"it-consulting","in":"IT Consulting","r":"london","rn":"London"},{"pn":"Mr Iheanacho Anthony Nnodi","pt":"i","n":"Xpendapay Limited","no":"16763627","t":"London","i":"it-consulting","in":"IT Consulting","r":"london","rn":"London"},{"pn":"Ms Ngozi Chukwuka Nnaife","pt":"i","n":"Grandline Tech Limited","no":"12498165","t":"London","i":"it-consulting","in":"IT Consulting","r":"london","rn":"London"},{"pn":"Promise Nnaka","pt":"i","n":"Tiaisa Intelligence & Security Consulting Ltd","no":"17012020","t":"London","i":"it-consulting","in":"IT Consulting","r":"london","rn":"London"},{"pn":"Mr Victor Chinedu Nnaukwu","pt":"i","n":"Source & Holdings Ltd","no":"16649371","t":"Manchester","i":"it-consulting","in":"IT Consulting","r":"north-west","rn":"North West England"},{"pn":"Mrs Ngozi Happiness Nneke","pt":"i","n":"Nnelin Tech Limited","no":"12657086","t":"Sale","i":"it-consulting","in":"IT Consulting","r":"north-west","rn":"North West England"},{"pn":"Mrs Ngozi Happiness Nneke","pt":"i","n":"Explana Ai Limited","no":"16692969","t":"Sale","i":"it-consulting","in":"IT Consulting","r":"north-west","rn":"North West England"},{"pn":"Mrs Chinwe Akudo Nnaji","pt":"i","n":"July Humphrey Consultants Ltd","no":"SC637486","t":"Glasgow","i":"it-consulting","in":"IT Consulting","r":"scotland","rn":"Scotland"},{"pn":"Mr Okechukwu Stanlislous Nnoli","pt":"i","n":"Professional Concepts Ltd","no":"SC467223","t":"Glasgow","i":"it-consulting","in":"IT Consulting","r":"scotland","rn":"Scotland"},{"pn":"Chinwe Akudo Nnaji","pt":"i","n":"Brighter Futures Initiative Cic","no":"SC601627","t":"Glasgow","i":"it-consulting","in":"IT Consulting","r":"scotland","rn":"Scotland"},{"pn":"Mr Edward Ugochukwu Nnadi","pt":"i","n":"Jean Edwards Consulting Limited","no":"08488479","t":"Brighton","i":"it-consulting","in":"IT Consulting","r":"south-east","rn":"South East England"},{"pn":"Mr Chukwudum Benjamin Nnam","pt":"i","n":"Golden Consults Limited","no":"13499106","t":"Birmingham","i":"it-consulting","in":"IT Consulting","r":"west-midlands","rn":"West Midlands"},{"pn":"Mrs Chioma Juliet Nnadi","pt":"i","n":"Jck Consulting Global Services Ltd","no":"16447313","t":"London","i":"it-services","in":"IT Services & Support","r":"london","rn":"London"},{"pn":"Ugochukwu Nnadi","pt":"i","n":"Enkora Limited","no":"16770809","t":"South Shields","i":"it-services","in":"IT Services & Support","r":"north-east","rn":"North East England"},{"pn":"Mrs Ngozi Happiness Nneke","pt":"i","n":"Tech Network Talent Cic","no":"16476449","t":"Manchester","i":"it-services","in":"IT Services & Support","r":"north-west","rn":"North West England"},{"pn":"Mr Anthony Nnadi","pt":"i","n":"Anadco Int'L Ltd","no":"06999540","t":"Liverpool","i":"it-services","in":"IT Services & Support","r":"north-west","rn":"North West England"},{"pn":"Mr Venantius Chibueze Nnoli","pt":"i","n":"Elyno Services Ltd","no":"11148587","t":"Cardiff","i":"it-services","in":"IT Services & Support","r":"wales","rn":"Wales"},{"pn":"Chidi Afamefuna Nnadozie","pt":"i","n":"Wagon Commerce Ltd","no":"16017108","t":"Cardiff","i":"it-services","in":"IT Services & Support","r":"wales","rn":"Wales"},{"pn":"Mr Hanson Nnadi","pt":"i","n":"Homely Ventures Ltd","no":"15803488","t":"Birmingham","i":"it-services","in":"IT Services & Support","r":"west-midlands","rn":"West Midlands"},{"pn":"Ms Anzelika Nnadi","pt":"i","n":"Str8 R8 Limited","no":"13535663","t":"Wickford","i":"management-consulting","in":"Management Consultancy","r":"east-england","rn":"East of England"},{"pn":"Mrs Catherine Oluwatoyin Nnamdi","pt":"i","n":"Tlconsultancy Limited","no":"09507999","t":"Lincoln","i":"management-consulting","in":"Management Consultancy","r":"east-midlands","rn":"East Midlands"},{"pn":"Dr Matthias Nnadi","pt":"i","n":"London Management Training Center Limited","no":"11518206","t":"Northampton","i":"management-consulting","in":"Management Consultancy","r":"east-midlands","rn":"East Midlands"},{"pn":"Mrs Ekwutosi Nnene","pt":"i","n":"Chookz Consulting Limited","no":"05828444","t":"London","i":"management-consulting","in":"Management Consultancy","r":"london","rn":"London"},{"pn":"Mr Nwachukwu Nwabueze Nnene","pt":"i","n":"Chookz Consulting Limited","no":"05828444","t":"London","i":"management-consulting","in":"Management Consultancy","r":"london","rn":"London"},{"pn":"Promise Nnaka","pt":"i","n":"Star Brands Consulting Ltd","no":"16667949","t":"London","i":"management-consulting","in":"Management Consultancy","r":"london","rn":"London"},{"pn":"Ms Vanessa Ola Nnachi-Uche","pt":"i","n":"Sui Generis 3Kngs Limited","no":"11690396","t":"Harrow","i":"management-consulting","in":"Management Consultancy","r":"london","rn":"London"},{"pn":"Mr Ifechukwu Nnatuanya","pt":"i","n":"Dpi Associates Limited","no":"05485914","t":"Mill Hill","i":"management-consulting","in":"Management Consultancy","r":"london","rn":"London"},{"pn":"Mrs Amaka Nnadi","pt":"i","n":"Jpgold Analytics Ltd","no":"11321354","t":"Hornchurch","i":"management-consulting","in":"Management Consultancy","r":"london","rn":"London"},{"pn":"Mr Franklin Nnah","pt":"i","n":"Frn Limited","no":"09829377","t":"London","i":"management-consulting","in":"Management Consultancy","r":"london","rn":"London"},{"pn":"Mr Ija Nnachi","pt":"i","n":"Ion Consulting Ltd","no":"15423887","t":"London","i":"management-consulting","in":"Management Consultancy","r":"london","rn":"London"},{"pn":"Mr Victor Nnajiofor Ogbodo Nnaji","pt":"i","n":"Von Enterprises Ltd","no":"16898688","t":"London","i":"management-consulting","in":"Management Consultancy","r":"london","rn":"London"},{"pn":"Dr Ifechukwu Henry Nnatuanya","pt":"i","n":"Action Research Network (Arn) Limited","no":"14218785","t":"Enfield","i":"management-consulting","in":"Management Consultancy","r":"london","rn":"London"},{"pn":"Mrs Arinola Nnatuanya","pt":"i","n":"Action Research Network (Arn) Limited","no":"14218785","t":"Enfield","i":"management-consulting","in":"Management Consultancy","r":"london","rn":"London"},{"pn":"Miss Rita Nnawuchi","pt":"i","n":"Eclipse Pharmreview Ltd","no":"11974740","t":"London","i":"management-consulting","in":"Management Consultancy","r":"london","rn":"London"},{"pn":"Ms Annabel Ona Chiazo Nnawuihe-Simpson","pt":"i","n":"Uncovered Agency Ltd","no":"15536505","t":"Belvedere","i":"management-consulting","in":"Management Consultancy","r":"london","rn":"London"},{"pn":"Ifechukwukwulu Nnatuanya","pt":"i","n":"Action Research Holdings Ltd","no":"17005789","t":"Enfield","i":"management-consulting","in":"Management Consultancy","r":"london","rn":"London"},{"pn":"Mr Michael Nnadede","pt":"i","n":"Michael Nnadede Ltd","no":"10343664","t":"Manchester","i":"management-consulting","in":"Management Consultancy","r":"north-west","rn":"North West England"},{"pn":"Mr Uzoma Chukwudubem Nnadi","pt":"i","n":"Ucn Consulting Limited","no":"SC637918","t":"Glasgow","i":"management-consulting","in":"Management Consultancy","r":"scotland","rn":"Scotland"},{"pn":"Mr Odera Nnaji","pt":"i","n":"Petrisurge Consulting Ltd","no":"SC827818","t":"Aberdeen","i":"management-consulting","in":"Management Consultancy","r":"scotland","rn":"Scotland"},{"pn":"Mrs Agnieszka Teresa Nnolim","pt":"i","n":"Toxicity And Human Body (Thb) Ltd","no":"14808458","t":"Crediton","i":"management-consulting","in":"Management Consultancy","r":"south-west","rn":"South West England"},{"pn":"Mrs Ekwutosi Nnene","pt":"i","n":"E.K Strategy Limited","no":"11400037","t":"Cardiff","i":"management-consulting","in":"Management Consultancy","r":"wales","rn":"Wales"},{"pn":"Mr Chukwudum Benjamin Nnam","pt":"i","n":"Golden Experts Ltd","no":"15442571","t":"Birmingham","i":"management-consulting","in":"Management Consultancy","r":"west-midlands","rn":"West Midlands"},{"pn":"Mrs Jane Nnawowo","pt":"i","n":"Pritur Ltd","no":"15786771","t":"Mildenhall","i":"marketing","in":"Marketing & Advertising","r":"east-england","rn":"East of England"},{"pn":"Mr Michael Caleb Nnaleche","pt":"i","n":"Alphamax Digital Services Limited","no":"15537984","t":"Luton","i":"marketing","in":"Marketing & Advertising","r":"east-england","rn":"East of England"},{"pn":"Mr Azuwike Zuwi Nnadi","pt":"i","n":"Lumi Digital Design Ltd","no":"13190522","t":"Bedford","i":"marketing","in":"Marketing & Advertising","r":"east-midlands","rn":"East Midlands"},{"pn":"Joseph Odinakachukwu Nna","pt":"i","n":"Labourer 11 Ltd","no":"16367936","t":"Milton Keynes","i":"marketing","in":"Marketing & Advertising","r":"east-midlands","rn":"East Midlands"},{"pn":"Miss Ifeoma Sophia Nnadi","pt":"i","n":"Black And Proud Cic","no":"15463847","t":"Nottingham","i":"marketing","in":"Marketing & Advertising","r":"east-midlands","rn":"East Midlands"},{"pn":"Miss Virginie Nnomo","pt":"i","n":"Virginie And Co Ltd","no":"15894423","t":"Leeds","i":"marketing","in":"Marketing & Advertising","r":"yorkshire","rn":"Yorkshire & Humber"},{"pn":"Mr Tochukwu Jonathan Nnabuchi","pt":"i","n":"Chito Procare And Decor Limited","no":"16181973","t":"Northampton","i":"plumbing","in":"Plumbing & Heating","r":"east-midlands","rn":"East Midlands"},{"pn":"Dr Ikechukwu Obidike Nnene","pt":"i","n":"Cidem Limited","no":"05839635","t":"Ipswich","i":"property-management","in":"Property Management","r":"east-england","rn":"East of England"},{"pn":"Mrs Amaka Sharon Nnanyelugo","pt":"i","n":"Luxuora Services Ltd","no":"16395639","t":"London","i":"property-management","in":"Property Management","r":"london","rn":"London"},{"pn":"Mr Tony Nnadi","pt":"i","n":"Tick Box Assets Ltd","no":"15559588","t":"London","i":"property-management","in":"Property Management","r":"london","rn":"London"},{"pn":"Julian Nnadi","pt":"i","n":"Ijn Services Ltd","no":"10616990","t":"London","i":"property-management","in":"Property Management","r":"london","rn":"London"},{"pn":"Ms Catherine Cressida Namagembe Nnyanzi","pt":"i","n":"The Katuntu Mansion Group Limited","no":"12014394","t":"Harlow","i":"property","in":"Property & Real Estate","r":"east-england","rn":"East of England"},{"pn":"Dr Ugochinyere Ngozi Nnorom","pt":"i","n":"Blooming Field Ltd","no":"15574581","t":"Harlow","i":"property","in":"Property & Real Estate","r":"east-england","rn":"East of England"},{"pn":"Mr Godson Ogechukwu Nnorom-Junior","pt":"i","n":"Blooming Field Ltd","no":"15574581","t":"Harlow","i":"property","in":"Property & Real Estate","r":"east-england","rn":"East of England"},{"pn":"Mr Uchenna Nnamani","pt":"i","n":"Nnabros Ltd","no":"16915910","t":"Luton","i":"property","in":"Property & Real Estate","r":"east-england","rn":"East of England"},{"pn":"Mrs Ene Nnamani","pt":"i","n":"Nnabros Ltd","no":"16915910","t":"Luton","i":"property","in":"Property & Real Estate","r":"east-england","rn":"East of England"},{"pn":"Mr Uchenna Nnamani","pt":"i","n":"Ed&P Solutions Ltd.","no":"07670581","t":"Luton","i":"property","in":"Property & Real Estate","r":"east-england","rn":"East of England"},{"pn":"Mrs Ene Nnamani","pt":"i","n":"Ed&P Solutions Ltd.","no":"07670581","t":"Luton","i":"property","in":"Property & Real Estate","r":"east-england","rn":"East of England"},{"pn":"Mr Uchenna Nnamani","pt":"i","n":"Ed&P Property Ltd","no":"12593963","t":"Luton","i":"property","in":"Property & Real Estate","r":"east-england","rn":"East of England"},{"pn":"Prof Kelechi Ebere Nnoaham","pt":"i","n":"Meriad Property Investments Ltd","no":"16365618","t":"Bury St. Edmunds","i":"property","in":"Property & Real Estate","r":"east-england","rn":"East of England"},{"pn":"Mrs Theodora Mmaegbunam Nnoaham","pt":"i","n":"Meriad Property Investments Ltd","no":"16365618","t":"Bury St. Edmunds","i":"property","in":"Property & Real Estate","r":"east-england","rn":"East of England"},{"pn":"Dr. Juliana Ngozi Nnadi","pt":"i","n":"Novara Property Investment Limited","no":"16804008","t":"Leicester","i":"property","in":"Property & Real Estate","r":"east-midlands","rn":"East Midlands"},{"pn":"Miss Ifeoma Sophia Nnadi","pt":"i","n":"Novara Property Investment Limited","no":"16804008","t":"Leicester","i":"property","in":"Property & Real Estate","r":"east-midlands","rn":"East Midlands"},{"pn":"Dr. Juliana Ngozi Nnadi","pt":"i","n":"Krestone Investment Limited","no":"12314118","t":"Leicester","i":"property","in":"Property & Real Estate","r":"east-midlands","rn":"East Midlands"},{"pn":"Miss Ifeoma Sophia Nnadi","pt":"i","n":"Krestone Investment Limited","no":"12314118","t":"Leicester","i":"property","in":"Property & Real Estate","r":"east-midlands","rn":"East Midlands"},{"pn":"Mr Frederick Emeka Nnaji","pt":"i","n":"Ocean Pyramids Ltd","no":"16842100","t":"Derby","i":"property","in":"Property & Real Estate","r":"east-midlands","rn":"East Midlands"},{"pn":"Mr Maduabuchi Nnadi","pt":"i","n":"Midas Touch Property Investments Limited","no":"13946178","t":"Peterborough","i":"property","in":"Property & Real Estate","r":"east-midlands","rn":"East Midlands"},{"pn":"Miss Phyllis Nnadi","pt":"i","n":"Jup Properties Ltd","no":"13576035","t":"Waltham Cross","i":"property","in":"Property & Real Estate","r":"london","rn":"London"},{"pn":"Mrs Cynthia Amaka Nnadi","pt":"i","n":"Ajgold Properties Ltd","no":"11832672","t":"Hornchurch","i":"property","in":"Property & Real Estate","r":"london","rn":"London"},{"pn":"Mr Emmanuel Chukwuemeka Nnadi","pt":"i","n":"Simids Properties Ltd","no":"16969926","t":"Barking","i":"property","in":"Property & Real Estate","r":"london","rn":"London"},{"pn":"Mrs Sylvia Ozichi Nnadi","pt":"i","n":"Simids Properties Ltd","no":"16969926","t":"Barking","i":"property","in":"Property & Real Estate","r":"london","rn":"London"},{"pn":"Mrs Grace Nnawuchi","pt":"i","n":"Cornerbrick Properties Ltd","no":"12105157","t":"London","i":"property","in":"Property & Real Estate","r":"london","rn":"London"},{"pn":"Mr Ikechi Justin Nnawuchi","pt":"i","n":"Cornerbrick Properties Ltd","no":"12105157","t":"London","i":"property","in":"Property & Real Estate","r":"london","rn":"London"},{"pn":"Mr Nnabuike Springvale Nnadede","pt":"i","n":"Nikerose Ltd","no":"14727597","t":"Pinner","i":"property","in":"Property & Real Estate","r":"london","rn":"London"},{"pn":"Mr Micheal Chinonso Nnaji","pt":"i","n":"Benmicheals Ltd","no":"15775320","t":"Welling","i":"property","in":"Property & Real Estate","r":"london","rn":"London"},{"pn":"Mr Alasdair Nnawuihe-Simpson","pt":"i","n":"Hove Avenue Holdings Ltd","no":"13324668","t":"London","i":"property","in":"Property & Real Estate","r":"london","rn":"London"},{"pn":"Mrs Rita Kofoworola Nnawuchi","pt":"i","n":"Medrx Limited","no":"07175992","t":"London","i":"property","in":"Property & Real Estate","r":"london","rn":"London"},{"pn":"Mr Ikechi Justin Nnawuchi","pt":"i","n":"Medrx Limited","no":"07175992","t":"London","i":"property","in":"Property & Real Estate","r":"london","rn":"London"},{"pn":"Miss Rehema Kiwanuka Nnabukeera","pt":"i","n":"Ridge Property Solutions Ltd","no":"10891427","t":"Stockport","i":"property","in":"Property & Real Estate","r":"north-west","rn":"North West England"},{"pn":"Kelechi Kennedy Nnabara","pt":"i","n":"Macans Global Services Limited","no":"16336658","t":"Salford","i":"property","in":"Property & Real Estate","r":"north-west","rn":"North West England"},{"pn":"Mr Chima Nnadi","pt":"i","n":"Bct Alliance Ltd","no":"SC745057","t":"Glasgow","i":"property","in":"Property & Real Estate","r":"scotland","rn":"Scotland"},{"pn":"Miss Rita Nnawuchi","pt":"i","n":"Rchn Limited","no":"12151078","t":"Chatham","i":"property","in":"Property & Real Estate","r":"south-east","rn":"South East England"},{"pn":"Mr Philip Nnadozie","pt":"i","n":"Bricks And Acres Ltd","no":"13838685","t":"Bristol","i":"property","in":"Property & Real Estate","r":"south-west","rn":"South West England"},{"pn":"Prof Kelechi Ebere Nnoaham","pt":"i","n":"Tomilmeriad Ltd","no":"16478268","t":"Cardiff","i":"property","in":"Property & Real Estate","r":"wales","rn":"Wales"},{"pn":"Dr Ikechukwu Henry Nnamani","pt":"i","n":"Henvia Limited","no":"16535205","t":"Newcastle","i":"property","in":"Property & Real Estate","r":"west-midlands","rn":"West Midlands"},{"pn":"Dr. Nnemdi Sylvia Nnamani","pt":"i","n":"Henvia Limited","no":"16535205","t":"Newcastle","i":"property","in":"Property & Real Estate","r":"west-midlands","rn":"West Midlands"},{"pn":"Mrs Mary Amarachi Nnaji","pt":"i","n":"Jaldum Enterprises Ltd","no":"17022029","t":"Birmingham","i":"property","in":"Property & Real Estate","r":"west-midlands","rn":"West Midlands"},{"pn":"Mrs Chioma Ken Nnamdi","pt":"i","n":"Mater Dei Limited","no":"14439787","t":"Doncaster","i":"property","in":"Property & Real Estate","r":"yorkshire","rn":"Yorkshire & Humber"},{"pn":"Mr. Gerald Uchenna Nnamokwor","pt":"i","n":"Luxor Gate Ltd","no":"16441007","t":"Pontefract","i":"property","in":"Property & Real Estate","r":"yorkshire","rn":"Yorkshire & Humber"},{"pn":"Ms Emmanuela Adaobi Nnanyelugo","pt":"i","n":"Radiant Carez Limited","no":"SC849839","t":"Falkirk","i":"recruitment","in":"Recruitment & Staffing","r":"scotland","rn":"Scotland"},{"pn":"Mr Chigbogwu Godwin Nnamani","pt":"i","n":"Edgesense Limited","no":"SC867620","t":"Glasgow","i":"recruitment","in":"Recruitment & Staffing","r":"scotland","rn":"Scotland"},{"pn":"Mr Obidinma Odinakachukwu Nnebe","pt":"i","n":"Kerla Limited","no":"16767547","t":"Hastings","i":"recruitment","in":"Recruitment & Staffing","r":"south-east","rn":"South East England"},{"pn":"Mr Stephen Onyinye Nnaka","pt":"i","n":"Lance Medical Ltd","no":"11312843","t":"Bristol","i":"recruitment","in":"Recruitment & Staffing","r":"south-west","rn":"South West England"},{"pn":"Ms Chidiogo Miracle Nnebe","pt":"i","n":"All Care Roles Uk Ltd","no":"16986657","t":"Wombwell","i":"recruitment","in":"Recruitment & Staffing","r":"yorkshire","rn":"Yorkshire & Humber"},{"pn":"Mr Osita Chijioke Nnaji","pt":"i","n":"Mission Homecare And Services Limited","no":"14814122","t":"Liversedge","i":"recruitment","in":"Recruitment & Staffing","r":"yorkshire","rn":"Yorkshire & Humber"},{"pn":"Mr. Sylvester Ndidiamaka Nnadi","pt":"i","n":"Nnadis Synergy Resources Limited","no":"15809944","t":"Lincoln","i":"research","in":"Research & Development","r":"east-midlands","rn":"East Midlands"},{"pn":"Mrs. Esther Ndidiamaka Nnadi","pt":"i","n":"Nnadis Synergy Resources Limited","no":"15809944","t":"Lincoln","i":"research","in":"Research & Development","r":"east-midlands","rn":"East Midlands"},{"pn":"Dr Ernest Okwudiri Nnadi","pt":"i","n":"Enpauly Research & Consultancy Limited","no":"08569639","t":"Nuneaton","i":"research","in":"Research & Development","r":"east-midlands","rn":"East Midlands"},{"pn":"Dr. Ngufor Corine Awonja Kalu Nnachi","pt":"i","n":"Airid Innovations Limited","no":"15369133","t":"Holborn","i":"research","in":"Research & Development","r":"london","rn":"London"},{"pn":"Mr Miles Edward Obinna Madaris Nnadi","pt":"i","n":"Helix Industries Ltd","no":"13851248","t":"Brighton","i":"research","in":"Research & Development","r":"south-east","rn":"South East England"},{"pn":"Mr Edward Ugochukwu Nnadi","pt":"i","n":"Helix Industries Ltd","no":"13851248","t":"Brighton","i":"research","in":"Research & Development","r":"south-east","rn":"South East England"},{"pn":"Mr Valentine Uchenna Nnadi","pt":"i","n":"Ekulu Restaurant Ltd","no":"15806937","t":"London","i":"restaurants","in":"Restaurants & Cafes","r":"london","rn":"London"},{"pn":"Mr Francis Nnaike","pt":"i","n":"Dizfam Ltd","no":"13118542","t":"Dagenham","i":"restaurants","in":"Restaurants & Cafes","r":"london","rn":"London"},{"pn":"Ms Benita Nnanna","pt":"i","n":"Tm'S Golden Spoon Cuisine Limited","no":"13455982","t":"Bournemouth","i":"restaurants","in":"Restaurants & Cafes","r":"south-west","rn":"South West England"},{"pn":"Mrs Uchechukwu Nneli","pt":"i","n":"Served  Group Limited","no":"14636846","t":"Birmingham","i":"restaurants","in":"Restaurants & Cafes","r":"west-midlands","rn":"West Midlands"},{"pn":"Mr Uche Onuegbu Nnabuife","pt":"i","n":"Merit Complete Package Ltd","no":"11524153","t":"London","i":"retail","in":"General Retail","r":"london","rn":"London"},{"pn":"Mrs Wofai Leko Nnannah","pt":"i","n":"Jawd Ltd","no":"14238690","t":"Carshalton","i":"retail","in":"General Retail","r":"london","rn":"London"},{"pn":"Mr Ifeanyi Nnamani","pt":"i","n":"Benchmarkin Prohub Ltd","no":"16233253","t":"London","i":"retail","in":"General Retail","r":"london","rn":"London"},{"pn":"Mr Uzoma Samuel Nnadi","pt":"i","n":"Ekinomo Ltd","no":"16500248","t":"Liverpool","i":"retail","in":"General Retail","r":"north-west","rn":"North West England"},{"pn":"Mr Chimdi Chukwusom Nnoli","pt":"i","n":"Chimcee Foods Ltd","no":"16269685","t":"Southampton","i":"retail","in":"General Retail","r":"south-east","rn":"South East England"},{"pn":"Benneth Onyebuchi Nnaneme","pt":"i","n":"Arikay Ltd","no":"16372191","t":"Maidstone","i":"retail","in":"General Retail","r":"south-east","rn":"South East England"},{"pn":"Mrs Victoria Nneji","pt":"i","n":"Kulynn Food Concept Ltd","no":"15484776","t":"Cardiff","i":"retail","in":"General Retail","r":"wales","rn":"Wales"},{"pn":"Mrs Nneamaka Mirian Nnebedum","pt":"i","n":"Teenymarty Ltd","no":"15581011","t":"Normanton","i":"retail","in":"General Retail","r":"yorkshire","rn":"Yorkshire & Humber"},{"pn":"Mr Michael Caleb Nnaleche","pt":"i","n":"Alphamax Security Limited","no":"16050756","t":"Luton","i":"security","in":"Security Services","r":"east-england","rn":"East of England"},{"pn":"Mr Kingsley Chukwudi Nnajiofor","pt":"i","n":"Solid Syndicate Ltd","no":"16603080","t":"Luton","i":"security","in":"Security Services","r":"east-england","rn":"East of England"},{"pn":"Mr Ambrose Nnadi","pt":"i","n":"Goodwill Security Ltd","no":"14255733","t":"London","i":"security","in":"Security Services","r":"london","rn":"London"},{"pn":"Mr Onyejiuwa Nnaji","pt":"i","n":"Elite Security Network Ltd","no":"16707479","t":"London","i":"security","in":"Security Services","r":"london","rn":"London"},{"pn":"Mr Emmanuel Nnadede","pt":"i","n":"Apogee Security Limited","no":"16359472","t":"Manchester","i":"security","in":"Security Services","r":"north-west","rn":"North West England"},{"pn":"Mr Victor Nnadi","pt":"i","n":"Vcn Tech Limited","no":"SC540794","t":"Aberdeen","i":"security","in":"Security Services","r":"scotland","rn":"Scotland"},{"pn":"Mr Fortune Ndubuisi Nnawuihe","pt":"i","n":"Fortunate Door Supervision Ltd","no":"11772937","t":"Oxford","i":"security","in":"Security Services","r":"south-east","rn":"South East England"},{"pn":"Mr Chigozie Kenneth Nnabuife","pt":"i","n":"Connectbingo Ltd","no":"16979755","t":"Hatfield","i":"software","in":"Software Development","r":"east-england","rn":"East of England"},{"pn":"Cally Nnamani","pt":"i","n":"Prometasoft Limited","no":"15635362","t":"Colchester","i":"software","in":"Software Development","r":"east-england","rn":"East of England"},{"pn":"Mr Paul James Nnaemeka","pt":"i","n":"P & A Corp Ltd","no":"15319026","t":"Coventry","i":"software","in":"Software Development","r":"east-midlands","rn":"East Midlands"},{"pn":"Mr Collins Obiora Nnaji","pt":"i","n":"Standex Digital Limited","no":"15642053","t":"Milton Keynes","i":"software","in":"Software Development","r":"east-midlands","rn":"East Midlands"},{"pn":"Mr Paul James Nnaemeka","pt":"i","n":"I & P Corp Ltd","no":"15953458","t":"Coventry","i":"software","in":"Software Development","r":"east-midlands","rn":"East Midlands"},{"pn":"Mr Praise Chibuike Nnadi","pt":"i","n":"Facetalk Ltd","no":"16684324","t":"Nottingham","i":"software","in":"Software Development","r":"east-midlands","rn":"East Midlands"},{"pn":"Mr Greg Chigozie Nnabuife","pt":"i","n":"Impulse Health Ltd","no":"16222290","t":"London","i":"software","in":"Software Development","r":"london","rn":"London"},{"pn":"Emmanuel Nnamani","pt":"i","n":"Web3County Ltd","no":"15099337","t":"Essex","i":"software","in":"Software Development","r":"london","rn":"London"},{"pn":"Mr Joseph Obinna Nnodim","pt":"i","n":"Werk Systems Limited","no":"16349200","t":"South Ockendon","i":"software","in":"Software Development","r":"london","rn":"London"},{"pn":"Mr Geoffery Nnalue","pt":"i","n":"The Circlesapp Ltd","no":"16261799","t":"London","i":"software","in":"Software Development","r":"london","rn":"London"},{"pn":"Ms Phillipa Nnanyere","pt":"i","n":"Outsourced Assignments Ltd","no":"16381404","t":"London","i":"software","in":"Software Development","r":"london","rn":"London"},{"pn":"Mr Henry Nnoli","pt":"i","n":"Threatlenz Ltd","no":"16842789","t":"London","i":"software","in":"Software Development","r":"london","rn":"London"},{"pn":"Chidi Nnaemeka Nnadi","pt":"i","n":"Maverick & Solace Ltd","no":"15947502","t":"London","i":"software","in":"Software Development","r":"london","rn":"London"},{"pn":"Mr Nnaemeka Stephen Nnamani","pt":"i","n":"Devcraft Labs Ltd","no":"16057511","t":"Newcastle Upon Tyne","i":"software","in":"Software Development","r":"north-east","rn":"North East England"},{"pn":"Mrs Ezinne Amanda Nnebocha","pt":"i","n":"Total Healthcare Technologies Ltd","no":"SC877220","t":"Aberdeen","i":"software","in":"Software Development","r":"scotland","rn":"Scotland"},{"pn":"Miss Solumtoochukwu Modesta Nnaemeka","pt":"i","n":"Hurray Enterprise Ltd","no":"16859295","t":"Cardiff","i":"software","in":"Software Development","r":"wales","rn":"Wales"},{"pn":"Miss Amarachi Nnochiri","pt":"i","n":"Vision Cure Ltd","no":"16456604","t":"Wolverhampton","i":"software","in":"Software Development","r":"west-midlands","rn":"West Midlands"},{"pn":"Mr Chukwunonso Nvene Nnamani","pt":"i","n":"Donche Ltd","no":"17046178","t":"Leeds","i":"software","in":"Software Development","r":"yorkshire","rn":"Yorkshire & Humber"},{"pn":"Antonia Nnyanzi","pt":"i","n":"Bridge Park Gymnastics Club Limited","no":"11692652","t":"Harlow","i":"sports","in":"Sports & Leisure Facilities","r":"east-england","rn":"East of England"},{"pn":"Mrs Juliet Amaka Nnajiaku","pt":"i","n":"Elilora & Co Ltd","no":"16548856","t":"Colchester","i":"taxis","in":"Taxis & Private Hire","r":"east-england","rn":"East of England"},{"pn":"Mr Michael Ikechukwu Nnabuike","pt":"i","n":"Mike Private Hire Limited","no":"15203333","t":"Huntingdon","i":"taxis","in":"Taxis & Private Hire","r":"east-midlands","rn":"East Midlands"},{"pn":"Miss Esther Nadia Nnoumoulolo","pt":"i","n":"Jf Chauffeur Services Limited","no":"15123527","t":"London","i":"taxis","in":"Taxis & Private Hire","r":"london","rn":"London"},{"pn":"Dr Ikechukwu Obidike Nnene","pt":"i","n":"Ike And Linda Limited","no":"08247673","t":"Norwich","i":"training","in":"Professional Training","r":"east-england","rn":"East of England"},{"pn":"Mrs Linda Onu Nnene","pt":"i","n":"Ike And Linda Limited","no":"08247673","t":"Norwich","i":"training","in":"Professional Training","r":"east-england","rn":"East of England"},{"pn":"Mrs Vera Chinelo Nnadozie","pt":"i","n":"Vera Chilly Consultancy Services Limited","no":"09466210","t":"Dunstable","i":"training","in":"Professional Training","r":"east-england","rn":"East of England"},{"pn":"Mr Prince Ike Panashe Nnadi","pt":"i","n":"Infoproductschool Limited","no":"15995276","t":"Coventry","i":"training","in":"Professional Training","r":"east-midlands","rn":"East Midlands"},{"pn":"Miss Fiona Nnanyere","pt":"i","n":"Cognitive Minds Ltd","no":"08734824","t":"Welling","i":"training","in":"Professional Training","r":"london","rn":"London"},{"pn":"Mr Uzoma Kenneth Nnajiuba","pt":"i","n":"Radcast Ltd","no":"16204533","t":"Huddersfield","i":"training","in":"Professional Training","r":"yorkshire","rn":"Yorkshire & Humber"},{"pn":"Mr Chidozie Nathaniel Nnadi","pt":"i","n":"Noace Property Group Ltd","no":"14770045","t":"London","i":"transport","in":"Road Transport & Haulage","r":"london","rn":"London"},{"pn":"Mr John Iheanyichukwu Nnorom","pt":"i","n":"Steadylogistics Ltd","no":"SC855638","t":"Ellon","i":"transport","in":"Road Transport & Haulage","r":"scotland","rn":"Scotland"},{"pn":"Mr Chukwudum Benjamin Nnam","pt":"i","n":"Golden Trail Ltd","no":"15673227","t":"Birmingham","i":"transport","in":"Road Transport & Haulage","r":"west-midlands","rn":"West Midlands"},{"pn":"Mr Chimezie Nnopu","pt":"i","n":"Marist Courier Services Ltd","no":"14751268","t":"Birmingham","i":"transport","in":"Road Transport & Haulage","r":"west-midlands","rn":"West Midlands"},{"pn":"Mr Victor Nnajiofor Ogbodo Nnaji","pt":"i","n":"Amaka Foods Ltd","no":"13464240","t":"Birmingham","i":"wholesale","in":"Wholesale & Distribution","r":"west-midlands","rn":"West Midlands"}]