[{"pn":"Miss Elif Ucar","pt":"i","n":"Elar Investment Ltd","no":"17048876","t":"London","i":"accommodation","in":"Guesthouses & B&Bs","r":"london","rn":"London"},{"pn":"Mr Resat Cemil Ucyigit","pt":"i","n":"Ru Accounting Consultancy Limited","no":"09480501","t":"Edgware","i":"accounting","in":"Accounting & Bookkeeping","r":"london","rn":"London"},{"pn":"Mrs Ijeoma Ogechi Uchendu","pt":"i","n":"Light Accountants Ltd","no":"12655598","t":"Sandwich","i":"accounting","in":"Accounting & Bookkeeping","r":"south-east","rn":"South East England"},{"pn":"Miss Dominika Deniz Ucar","pt":"i","n":"Deadweight Theatre Ltd","no":"14481405","t":"London","i":"arts","in":"Arts & Entertainment","r":"london","rn":"London"},{"pn":"Mitsuko Uchida","pt":"i","n":"Tanuki Music Company (U.K.) Limited","no":"01869809","t":"London","i":"arts","in":"Arts & Entertainment","r":"london","rn":"London"},{"pn":"Chukwuebuka Godwin Uchendu","pt":"i","n":"Kiez Holding Ltd","no":"16801985","t":"London","i":"automotive","in":"Car Sales & Automotive","r":"london","rn":"London"},{"pn":"Mr Huseyin Ucur","pt":"i","n":"Ucur Hiya Renta Ltd","no":"16254090","t":"London","i":"automotive","in":"Car Sales & Automotive","r":"london","rn":"London"},{"pn":"Mr Lukasz Kamil Ucher","pt":"i","n":"Ucher Body Repair Ltd","no":"12388395","t":"Greenford","i":"automotive","in":"Car Sales & Automotive","r":"london","rn":"London"},{"pn":"Miss Nurcan Ucak","pt":"i","n":"Gnk Beauty Ltd","no":"16035702","t":"Clacton On Sea","i":"beauty","in":"Hair & Beauty","r":"east-england","rn":"East of England"},{"pn":"Mr Ali Ucer","pt":"i","n":"Ozgur Gents Ltd","no":"09052411","t":"Cambridge","i":"beauty","in":"Hair & Beauty","r":"east-england","rn":"East of England"},{"pn":"Halit Ucar","pt":"i","n":"Istanbul Turkish Barber (Alton) Ltd","no":"14015465","t":"London","i":"beauty","in":"Hair & Beauty","r":"london","rn":"London"},{"pn":"Mr Mehmet Selim Ucar","pt":"i","n":"A&S Hairdressing Services Ltd","no":"14516235","t":"London","i":"beauty","in":"Hair & Beauty","r":"london","rn":"London"},{"pn":"Mrs Yasemin Ucar","pt":"i","n":"Jasmin Beauty London Ltd","no":"13479035","t":"London","i":"beauty","in":"Hair & Beauty","r":"london","rn":"London"},{"pn":"Mr Ahmet Ucar","pt":"i","n":"Istanbul Fleet Barber Ltd","no":"14615623","t":"London","i":"beauty","in":"Hair & Beauty","r":"london","rn":"London"},{"pn":"Mr Muhammed Berzan Ucar","pt":"i","n":"Ton 2 Sil Ltd","no":"16740671","t":"Addlestone","i":"beauty","in":"Hair & Beauty","r":"london","rn":"London"},{"pn":"Mr Salman Ucer","pt":"i","n":"Ucsa Barbers Ltd","no":"15155913","t":"London","i":"beauty","in":"Hair & Beauty","r":"london","rn":"London"},{"pn":"Mr Salman Ucer","pt":"i","n":"Salmen Barber Shop Ltd","no":"14495568","t":"London","i":"beauty","in":"Hair & Beauty","r":"london","rn":"London"},{"pn":"Mr Ali Ucer","pt":"i","n":"Ucer Barbers Ltd","no":"14947322","t":"London","i":"beauty","in":"Hair & Beauty","r":"london","rn":"London"},{"pn":"Mr Ramazan Ucer","pt":"i","n":"Istanbul Barber Brighton Ltd","no":"12524302","t":"London","i":"beauty","in":"Hair & Beauty","r":"london","rn":"London"},{"pn":"Mr Murat Ucar","pt":"i","n":"Renasucr Ltd","no":"15571773","t":"Waltham Abbey","i":"beauty","in":"Hair & Beauty","r":"london","rn":"London"},{"pn":"Murat Ucar","pt":"i","n":"Moss Barbers Ltd","no":"13085349","t":"London","i":"beauty","in":"Hair & Beauty","r":"london","rn":"London"},{"pn":"Miss Melis Ucar","pt":"i","n":"Moss Barbers Ltd","no":"13085349","t":"London","i":"beauty","in":"Hair & Beauty","r":"london","rn":"London"},{"pn":"Mr Salman Ucer","pt":"i","n":"Salman Hairstyle Ltd","no":"12883578","t":"London","i":"beauty","in":"Hair & Beauty","r":"london","rn":"London"},{"pn":"Mr Ramazan Ucer","pt":"i","n":"Lions London 2025 Limited","no":"16188696","t":"Romford","i":"beauty","in":"Hair & Beauty","r":"london","rn":"London"},{"pn":"Mr Salman Ucer","pt":"i","n":"Mehmet Ali Ltd","no":"10477901","t":"London","i":"beauty","in":"Hair & Beauty","r":"london","rn":"London"},{"pn":"Mr Zeynal Abidin Ucar","pt":"i","n":"Carbon Clinic Ltd","no":"14935037","t":"London","i":"beauty","in":"Hair & Beauty","r":"london","rn":"London"},{"pn":"Mrs Enkelejda Uci","pt":"i","n":"Shiny Nails Limited","no":"16134561","t":"London","i":"beauty","in":"Hair & Beauty","r":"london","rn":"London"},{"pn":"Mr Zeynal Abidin Ucar","pt":"i","n":"Hf Studio Ltd","no":"15136070","t":"London","i":"beauty","in":"Hair & Beauty","r":"london","rn":"London"},{"pn":"Mr Salman Ucer","pt":"i","n":"Barber Lounge Claygate Ltd","no":"16711479","t":"London","i":"beauty","in":"Hair & Beauty","r":"london","rn":"London"},{"pn":"Miss Paige Stevie Anna Uche","pt":"i","n":"P B Beauty Ltd","no":"15834135","t":"London","i":"beauty","in":"Hair & Beauty","r":"london","rn":"London"},{"pn":"Ms Saniye Ucku","pt":"i","n":"Nova Salon Limited","no":"15274415","t":"Orpington","i":"beauty","in":"Hair & Beauty","r":"london","rn":"London"},{"pn":"Mr Muhammed Berzan Ucar","pt":"i","n":"Tonsil Ltd","no":"15710398","t":"London","i":"beauty","in":"Hair & Beauty","r":"london","rn":"London"},{"pn":"Mr Zeynal Abidin Ucar","pt":"i","n":"Midtown Barbers Ltd","no":"11714810","t":"London","i":"beauty","in":"Hair & Beauty","r":"london","rn":"London"},{"pn":"Christian Uchime","pt":"i","n":"Ujari Merchant Limited","no":"14709705","t":"London","i":"beauty","in":"Hair & Beauty","r":"london","rn":"London"},{"pn":"Mr Mehmet Selim Ucar","pt":"i","n":"Selim Pasha Ltd","no":"16498487","t":"London","i":"beauty","in":"Hair & Beauty","r":"london","rn":"London"},{"pn":"Mr Abdullah Ucar","pt":"i","n":"City'S Barbers Limited","no":"10826595","t":"Newcastle Upon Tyne","i":"beauty","in":"Hair & Beauty","r":"north-east","rn":"North East England"},{"pn":"Mr Ridvan Ucar","pt":"i","n":"My Mobile Barber Ltd","no":"13134597","t":"Newcastle Upon Tyne","i":"beauty","in":"Hair & Beauty","r":"north-east","rn":"North East England"},{"pn":"Kursat Ucar","pt":"i","n":"The Cousins Barber Shop Ltd","no":"NI725628","t":"Enniskillen","i":"beauty","in":"Hair & Beauty","r":"northern-ireland","rn":"Northern Ireland"},{"pn":"Kursat Ucar","pt":"i","n":"Aras Barbershop Ltd","no":"NI733358","t":"Portstewart","i":"beauty","in":"Hair & Beauty","r":"northern-ireland","rn":"Northern Ireland"},{"pn":"Mr Sabir Ucar","pt":"i","n":"The Renfrew Barber Ltd","no":"SC652378","t":"Renfrew","i":"beauty","in":"Hair & Beauty","r":"scotland","rn":"Scotland"},{"pn":"Mrs Fiona Ucar","pt":"i","n":"The Renfrew Barber Ltd","no":"SC652378","t":"Renfrew","i":"beauty","in":"Hair & Beauty","r":"scotland","rn":"Scotland"},{"pn":"Mr Dennis Ucar","pt":"i","n":"Mrbarberscunthorpe Ltd","no":"16031553","t":"Scunthorpe","i":"beauty","in":"Hair & Beauty","r":"yorkshire","rn":"Yorkshire & Humber"},{"pn":"Ms Rita Ucheobi","pt":"i","n":"House Of C&C Ltd","no":"16622966","t":"Leeds","i":"beauty","in":"Hair & Beauty","r":"yorkshire","rn":"Yorkshire & Humber"},{"pn":"Mrs. Elvira Uchaeva","pt":"i","n":"Home Services A&A Ltd","no":"11170029","t":"Hatfield","i":"building-services","in":"Building Services","r":"east-england","rn":"East of England"},{"pn":"Mr Jashilal Ucaro","pt":"i","n":"Soho Mark Ltd","no":"12445909","t":"Leicester","i":"building-services","in":"Building Services","r":"east-midlands","rn":"East Midlands"},{"pn":"Mr Ikechukwu Uchendu","pt":"i","n":"Unik Drylining Ltd","no":"11490641","t":"Gravesend","i":"building-services","in":"Building Services","r":"london","rn":"London"},{"pn":"Mr Kevin Uche","pt":"i","n":"K & O (Uk) Limited","no":"07688999","t":"Gravesend","i":"building-services","in":"Building Services","r":"london","rn":"London"},{"pn":"Mr Murat Ucar","pt":"i","n":"Slay Building Ltd","no":"12578515","t":"London","i":"building-services","in":"Building Services","r":"london","rn":"London"},{"pn":"Mr Augustine Onwuchuruba Uchehara","pt":"i","n":"Austina Limited","no":"13865312","t":"London","i":"building-services","in":"Building Services","r":"london","rn":"London"},{"pn":"Mr Chinedu Henry Uchenabo","pt":"i","n":"Exceptional Property Development Ltd","no":"16795262","t":"Croydon","i":"building-services","in":"Building Services","r":"london","rn":"London"},{"pn":"Refat Feraidoon Uchqoon","pt":"i","n":"Bexsa Ltd","no":"15871521","t":"Ruislip,","i":"building-services","in":"Building Services","r":"london","rn":"London"},{"pn":"Mr Grzegorz Rafal Uchwat","pt":"i","n":"Uw Renders Ltd","no":"12309122","t":"Stoke-On-Trent","i":"building-services","in":"Building Services","r":"west-midlands","rn":"West Midlands"},{"pn":"Ms Sibel Ucur","pt":"i","n":"Mylandix Events Ltd","no":"14135810","t":"London","i":"catering","in":"Event Catering","r":"london","rn":"London"},{"pn":"Mr Hasan Ucar","pt":"i","n":"Cafe Alan Limited","no":"08444706","t":"London","i":"catering","in":"Event Catering","r":"london","rn":"London"},{"pn":"Miss Olive Adaoma Uche","pt":"i","n":"D Olive'S Kitchen Ltd","no":"16423844","t":"Salford","i":"catering","in":"Event Catering","r":"north-west","rn":"North West England"},{"pn":"Miss Seda Ucer","pt":"i","n":"Seda Events Ltd","no":"SC717010","t":"Aberdeen","i":"catering","in":"Event Catering","r":"scotland","rn":"Scotland"},{"pn":"Ferdinard Oghenefejiro Ucho","pt":"i","n":"F.I.D. Integrated Services Ltd","no":"17005482","t":"Canterbury","i":"catering","in":"Event Catering","r":"south-east","rn":"South East England"},{"pn":"Mr Serkan Ucar","pt":"i","n":"Flys Catering Ltd","no":"12679519","t":"Cleethorpes","i":"catering","in":"Event Catering","r":"yorkshire","rn":"Yorkshire & Humber"},{"pn":"Mrs Ada Peace Uchegbu","pt":"i","n":"Homeland Delicacy Limited","no":"11560239","t":"Rotherham","i":"catering","in":"Event Catering","r":"yorkshire","rn":"Yorkshire & Humber"},{"pn":"Mr Chima Daniel Uchechi","pt":"i","n":"Harmony Hill Daycare Nursery Ltd","no":"16229479","t":"London","i":"childcare","in":"Childcare & Day Nurseries","r":"london","rn":"London"},{"pn":"Miss Chioma Nnenna Uchendu","pt":"i","n":"Benc Limited","no":"15367607","t":"Nottingham","i":"cleaning","in":"Commercial Cleaning","r":"east-midlands","rn":"East Midlands"},{"pn":"Mrs Samantha Uche","pt":"i","n":"Clean360 U.K Ltd","no":"14288662","t":"Derby","i":"cleaning","in":"Commercial Cleaning","r":"east-midlands","rn":"East Midlands"},{"pn":"Mr Sunday Chinedu Uche","pt":"i","n":"Clean360 Ltd","no":"09725067","t":"Derby","i":"cleaning","in":"Commercial Cleaning","r":"east-midlands","rn":"East Midlands"},{"pn":"Mr Lucian Ucrainet","pt":"i","n":"Lucian & Lucia Limited","no":"15925185","t":"Watford","i":"cleaning","in":"Commercial Cleaning","r":"london","rn":"London"},{"pn":"Ms Uzochukwu Faith Uchendu","pt":"i","n":"Eliora Cleaning Services Limited","no":"10534142","t":"London","i":"cleaning","in":"Commercial Cleaning","r":"london","rn":"London"},{"pn":"Ms Sevgi Uckayabasi","pt":"i","n":"Uk Dogu Ltd","no":"15326203","t":"Chelmsford","i":"construction","in":"Construction","r":"east-england","rn":"East of England"},{"pn":"Mr Sercihan Yusuf Ucur","pt":"i","n":"Greenbrook Investment (Milton Keynes) Ltd","no":"15245594","t":"Buckinghamshire","i":"construction","in":"Construction","r":"east-midlands","rn":"East Midlands"},{"pn":"Mr Ion Eduard Uca","pt":"i","n":"Ef Roofing &Construction Ltd","no":"13645987","t":"Milton Keynes","i":"construction","in":"Construction","r":"east-midlands","rn":"East Midlands"},{"pn":"Mr Lutfi Ucal","pt":"i","n":"Designpincer Ltd","no":"11022723","t":"Nottingham","i":"construction","in":"Construction","r":"east-midlands","rn":"East Midlands"},{"pn":"Ms Ina Ucrainet","pt":"i","n":"Volnik Ltd","no":"09955484","t":"Northampton","i":"construction","in":"Construction","r":"east-midlands","rn":"East Midlands"},{"pn":"Mr Kemal Ucur","pt":"i","n":"Myra Developments Limited","no":"12985294","t":"Waltham Cross","i":"construction","in":"Construction","r":"london","rn":"London"},{"pn":"Mrs Yildiz Ucur","pt":"i","n":"Myra Developments Limited","no":"12985294","t":"Waltham Cross","i":"construction","in":"Construction","r":"london","rn":"London"},{"pn":"Mrs. Elvira Uchaeva","pt":"i","n":"El Property Management Ltd","no":"12280676","t":"London","i":"construction","in":"Construction","r":"london","rn":"London"},{"pn":"Mr Pawel Uczciwek","pt":"i","n":"Xresidence Ltd","no":"13524409","t":"Enfield","i":"construction","in":"Construction","r":"london","rn":"London"},{"pn":"Mr Baris Ucar","pt":"i","n":"Ucr Decor Ltd","no":"16922473","t":"Enfield","i":"construction","in":"Construction","r":"london","rn":"London"},{"pn":"Mr Chinedu Henry Uchenabo","pt":"i","n":"Exceptional Developments Limited","no":"15504836","t":"Croydon","i":"construction","in":"Construction","r":"london","rn":"London"},{"pn":"Mr Ercan Ucur","pt":"i","n":"Monty Supermarket Limited","no":"10485999","t":"Harrow","i":"construction","in":"Construction","r":"london","rn":"London"},{"pn":"Mr Umit Ucar","pt":"i","n":"Mss Camden Ltd","no":"15964065","t":"London","i":"construction","in":"Construction","r":"london","rn":"London"},{"pn":"Mrs Turkan Ucur","pt":"i","n":"Vesta Investments Management Limited","no":"13748479","t":"London","i":"construction","in":"Construction","r":"london","rn":"London"},{"pn":"Mrs Adaobi Onyinye Uchendu","pt":"i","n":"Adsam Limited","no":"10184771","t":"Tilbury","i":"construction","in":"Construction","r":"london","rn":"London"},{"pn":"Mr Samuel Chinedu Uchendu","pt":"i","n":"Adsam Limited","no":"10184771","t":"Tilbury","i":"construction","in":"Construction","r":"london","rn":"London"},{"pn":"Mr Marius Marcel Ucrainet","pt":"i","n":"M Expert Construction Ltd","no":"11309039","t":"Watford","i":"construction","in":"Construction","r":"london","rn":"London"},{"pn":"Nikolay Anastasov Uchkunov","pt":"i","n":"Alex98 Ltd","no":"10414116","t":"Romford","i":"construction","in":"Construction","r":"london","rn":"London"},{"pn":"Mrs Daniela Sorina Ucrainet","pt":"i","n":"D Property Maintenance Limited","no":"15461718","t":"Watford","i":"construction","in":"Construction","r":"london","rn":"London"},{"pn":"Mrs Michelle Uche-Kaine","pt":"i","n":"Michelle Kaine Properties Limited","no":"16056267","t":"London","i":"construction","in":"Construction","r":"london","rn":"London"},{"pn":"Mr Abbas Uce","pt":"i","n":"A Uce Construction Ltd","no":"16423343","t":"London","i":"construction","in":"Construction","r":"london","rn":"London"},{"pn":"Dr Nicole Uchenna Uchendu","pt":"i","n":"Blose Construction Limited","no":"13217769","t":"Westerham","i":"construction","in":"Construction","r":"south-east","rn":"South East England"},{"pn":"Mr Joseph Uche","pt":"i","n":"Jocharl Services Limited","no":"10119990","t":"Basildon","i":"consultancy","in":"Business Consultancy","r":"east-england","rn":"East of England"},{"pn":"Dr Olga Ucar","pt":"i","n":"Parse Medical Limited","no":"16102428","t":"Uxbridge","i":"consultancy","in":"Business Consultancy","r":"london","rn":"London"},{"pn":"Dr Ahmet Ucar","pt":"i","n":"Parse Medical Limited","no":"16102428","t":"Uxbridge","i":"consultancy","in":"Business Consultancy","r":"london","rn":"London"},{"pn":"Mr Mark Uckermann","pt":"i","n":"Chamox Technology Ltd","no":"12908262","t":"Preston","i":"consultancy","in":"Business Consultancy","r":"north-west","rn":"North West England"},{"pn":"Mrs Kenechi Uche","pt":"i","n":"Thekays Limited","no":"16815510","t":"Southampton","i":"consultancy","in":"Business Consultancy","r":"south-east","rn":"South East England"},{"pn":"Mr David Chijioke Uchechukwu-Chijioke","pt":"i","n":"365 Commercial Holdings Limited","no":"15941472","t":"London","i":"data-services","in":"Data Processing & Hosting","r":"london","rn":"London"},{"pn":"Mr Oktay Ucar","pt":"i","n":"Ready Hill Ltd","no":"15730405","t":"Welwyn Garden City","i":"ecommerce","in":"Online Retail & E-commerce","r":"east-england","rn":"East of England"},{"pn":"Mr Okwuchukwu Francis Uchendu","pt":"i","n":"Kayz Mall Limited","no":"15755742","t":"Mildenhall.","i":"ecommerce","in":"Online Retail & E-commerce","r":"east-england","rn":"East of England"},{"pn":"Mr Kadir Ucar","pt":"i","n":"Ucr Ltd","no":"16157980","t":"London","i":"ecommerce","in":"Online Retail & E-commerce","r":"london","rn":"London"},{"pn":"Mr Orhan Ucar","pt":"i","n":"Ucar7 Ltd","no":"17004628","t":"London","i":"ecommerce","in":"Online Retail & E-commerce","r":"london","rn":"London"},{"pn":"Mr Orhan Ucar","pt":"i","n":"Ucar8 Ltd","no":"17004631","t":"London","i":"ecommerce","in":"Online Retail & E-commerce","r":"london","rn":"London"},{"pn":"Mr Orhan Ucar","pt":"i","n":"Ucar9 Ltd","no":"17004635","t":"London","i":"ecommerce","in":"Online Retail & E-commerce","r":"london","rn":"London"},{"pn":"Mr Muhammed Ali Uces","pt":"i","n":"Marvard Ltd","no":"14627704","t":"Highgate","i":"ecommerce","in":"Online Retail & E-commerce","r":"london","rn":"London"},{"pn":"Hakan Ucuncu","pt":"i","n":"Thirdfamily Ltd","no":"15177391","t":"London","i":"ecommerce","in":"Online Retail & E-commerce","r":"london","rn":"London"},{"pn":"Mr Orhan Ucar","pt":"i","n":"Ucar2 Ltd","no":"17000690","t":"London","i":"ecommerce","in":"Online Retail & E-commerce","r":"london","rn":"London"},{"pn":"Mr Orhan Ucar","pt":"i","n":"Ucar4 Ltd","no":"17000671","t":"London","i":"ecommerce","in":"Online Retail & E-commerce","r":"london","rn":"London"},{"pn":"Mr Orhan Ucar","pt":"i","n":"Ucar5 Ltd","no":"17000679","t":"London","i":"ecommerce","in":"Online Retail & E-commerce","r":"london","rn":"London"},{"pn":"Mr Orhan Ucar","pt":"i","n":"Ucar6 Ltd","no":"17003751","t":"London","i":"ecommerce","in":"Online Retail & E-commerce","r":"london","rn":"London"},{"pn":"Mrs Esin Ucar","pt":"i","n":"Essyn Life And Style Ltd","no":"11797956","t":"Bexley","i":"ecommerce","in":"Online Retail & E-commerce","r":"london","rn":"London"},{"pn":"Mr Alim Ucar","pt":"i","n":"Mfy Trade Limited","no":"12127437","t":"London","i":"ecommerce","in":"Online Retail & E-commerce","r":"london","rn":"London"},{"pn":"Ms Angela Uchendu","pt":"i","n":"Gfitgear Ltd","no":"16999628","t":"London","i":"ecommerce","in":"Online Retail & E-commerce","r":"london","rn":"London"},{"pn":"Mr Mustafa Kemal Ucar","pt":"i","n":"Arda Trend Ltd","no":"15449943","t":"Richmond","i":"ecommerce","in":"Online Retail & E-commerce","r":"london","rn":"London"},{"pn":"Mrs Ezgi Bicer Ucar","pt":"i","n":"Arda Trend Ltd","no":"15449943","t":"Richmond","i":"ecommerce","in":"Online Retail & E-commerce","r":"london","rn":"London"},{"pn":"Mr Ufuk Ucar","pt":"i","n":"Svooy Ltd","no":"15098908","t":"London","i":"ecommerce","in":"Online Retail & E-commerce","r":"london","rn":"London"},{"pn":"Mr Orhan Ucar","pt":"i","n":"Ucar1 Ltd","no":"16996011","t":"London","i":"ecommerce","in":"Online Retail & E-commerce","r":"london","rn":"London"},{"pn":"Mr Nazmi Ucar","pt":"i","n":"Pet Paradise 1 Ltd","no":"15806840","t":"London","i":"ecommerce","in":"Online Retail & E-commerce","r":"london","rn":"London"},{"pn":"Ms Seyhan Ucar","pt":"i","n":"Godelek Group Ltd","no":"16348547","t":"Enfield","i":"ecommerce","in":"Online Retail & E-commerce","r":"london","rn":"London"},{"pn":"Mr Fuat Ucar","pt":"i","n":"Senvoza Ltd","no":"16742141","t":"London","i":"ecommerce","in":"Online Retail & E-commerce","r":"london","rn":"London"},{"pn":"Mr Harun Ucan","pt":"i","n":"Levoria Ltd","no":"17049852","t":"London","i":"ecommerce","in":"Online Retail & E-commerce","r":"london","rn":"London"},{"pn":"Mr Muhammed Ucar","pt":"i","n":"Rhetro Global Ltd","no":"16464107","t":"London","i":"ecommerce","in":"Online Retail & E-commerce","r":"london","rn":"London"},{"pn":"Mrs Makbule Ucar","pt":"i","n":"3B Ucr Limited","no":"16268857","t":"London","i":"ecommerce","in":"Online Retail & E-commerce","r":"london","rn":"London"},{"pn":"Mr Mehmet Kemal Uckuyu","pt":"i","n":"Aternum Ltd","no":"16267140","t":"London","i":"ecommerce","in":"Online Retail & E-commerce","r":"london","rn":"London"},{"pn":"Mr Gavin Marc Ucko","pt":"i","n":"The Happy Puzzle Company Limited","no":"02781931","t":"Sidcup","i":"ecommerce","in":"Online Retail & E-commerce","r":"london","rn":"London"},{"pn":"Mrs Rachel Roberta Ucko","pt":"i","n":"The Happy Puzzle Company Limited","no":"02781931","t":"Sidcup","i":"ecommerce","in":"Online Retail & E-commerce","r":"london","rn":"London"},{"pn":"Ozer Ucar","pt":"i","n":"Uniq Trio Consulting Limited","no":"13692854","t":"London","i":"ecommerce","in":"Online Retail & E-commerce","r":"london","rn":"London"},{"pn":"Ebru Sahin Ucar","pt":"i","n":"Uniq Trio Consulting Limited","no":"13692854","t":"London","i":"ecommerce","in":"Online Retail & E-commerce","r":"london","rn":"London"},{"pn":"Semra Ucar","pt":"i","n":"Ucar3 Limited","no":"16728021","t":"Enfield","i":"ecommerce","in":"Online Retail & E-commerce","r":"london","rn":"London"},{"pn":"Mr Akin Ucok","pt":"i","n":"Psd Poseidon Global Consulting Ltd","no":"12889792","t":"London","i":"ecommerce","in":"Online Retail & E-commerce","r":"london","rn":"London"},{"pn":"Mr Hikmet Ucar","pt":"i","n":"E-Marcia Ltd","no":"13209590","t":"London","i":"ecommerce","in":"Online Retail & E-commerce","r":"london","rn":"London"},{"pn":"Mr Harun Uchak","pt":"i","n":"Ucak Limited","no":"14111895","t":"London","i":"ecommerce","in":"Online Retail & E-commerce","r":"london","rn":"London"},{"pn":"Mrs Efsun Ecem Uckardes","pt":"i","n":"Akhlys Ltd","no":"15416870","t":"London","i":"ecommerce","in":"Online Retail & E-commerce","r":"london","rn":"London"},{"pn":"Mustafa Uctas","pt":"i","n":"Et Globall Ltd","no":"16079392","t":"London","i":"ecommerce","in":"Online Retail & E-commerce","r":"london","rn":"London"},{"pn":"Founder Cetin Nevzat Ucar","pt":"i","n":"Xan Media Ltd","no":"15348383","t":"London","i":"ecommerce","in":"Online Retail & E-commerce","r":"london","rn":"London"},{"pn":"Founder Zeynep Aytekin Ucar","pt":"i","n":"Xan Media Ltd","no":"15348383","t":"London","i":"ecommerce","in":"Online Retail & E-commerce","r":"london","rn":"London"},{"pn":"Mr Cankat Ucar","pt":"i","n":"Third Party Supply Ltd","no":"16776957","t":"London","i":"ecommerce","in":"Online Retail & E-commerce","r":"london","rn":"London"},{"pn":"Mr Ismail Ucaravci","pt":"i","n":"Dois Business Ltd","no":"16441017","t":"London","i":"ecommerce","in":"Online Retail & E-commerce","r":"london","rn":"London"},{"pn":"Saban Ucar","pt":"i","n":"Boonzie Ltd","no":"16120656","t":"Epsom","i":"ecommerce","in":"Online Retail & E-commerce","r":"london","rn":"London"},{"pn":"Mrs Danuzza De Goes Uchoa","pt":"i","n":"Jclog Digital Business Limited","no":"16829089","t":"London","i":"ecommerce","in":"Online Retail & E-commerce","r":"london","rn":"London"},{"pn":"Mr Turan Ucar","pt":"i","n":"Miravon Ltd","no":"16761103","t":"London","i":"ecommerce","in":"Online Retail & E-commerce","r":"london","rn":"London"},{"pn":"Mr Adem Uckun","pt":"i","n":"Vorte Ltd","no":"16559218","t":"London","i":"ecommerce","in":"Online Retail & E-commerce","r":"london","rn":"London"},{"pn":"Mr Antonio Ucovic","pt":"i","n":"Maids Touch Ltd","no":"14776271","t":"London","i":"ecommerce","in":"Online Retail & E-commerce","r":"london","rn":"London"},{"pn":"Mr Orhan Ucar","pt":"i","n":"3B Ucar Limited","no":"16225970","t":"London","i":"ecommerce","in":"Online Retail & E-commerce","r":"london","rn":"London"},{"pn":"Mr Ufuk Ucar","pt":"i","n":"Istventures Ltd","no":"15044298","t":"London","i":"ecommerce","in":"Online Retail & E-commerce","r":"london","rn":"London"},{"pn":"Mrs Oleksandra Uckun","pt":"i","n":"Beautyboostr Ltd.","no":"16938868","t":"London","i":"ecommerce","in":"Online Retail & E-commerce","r":"london","rn":"London"},{"pn":"Mr Chidozie Victor Uche","pt":"i","n":"Stockmall Ltd","no":"16778129","t":"Manchester","i":"ecommerce","in":"Online Retail & E-commerce","r":"north-west","rn":"North West England"},{"pn":"Mr Bright Obinna Uchemadu","pt":"i","n":"Hairsbymeme Ltd","no":"SC840465","t":"Glasgow","i":"ecommerce","in":"Online Retail & E-commerce","r":"scotland","rn":"Scotland"},{"pn":"Miss Ijeoma Ogechi Uchendu","pt":"i","n":"Kejay Limited","no":"11009123","t":"Sandwich","i":"ecommerce","in":"Online Retail & E-commerce","r":"south-east","rn":"South East England"},{"pn":"Kenechi Clementina Uchenna","pt":"i","n":"Empire Stores Ltd","no":"16903105","t":"Southampton","i":"ecommerce","in":"Online Retail & E-commerce","r":"south-east","rn":"South East England"},{"pn":"Nkiruka Nwabundo Uchenna","pt":"i","n":"Sugarplumun Ltd","no":"16783559","t":"Bristol","i":"ecommerce","in":"Online Retail & E-commerce","r":"south-west","rn":"South West England"},{"pn":"Mr Tarkan Ucar","pt":"i","n":"Ucar Commerce Ltd","no":"16118753","t":"Cardiff","i":"ecommerce","in":"Online Retail & E-commerce","r":"wales","rn":"Wales"},{"pn":"Mr Burak Uca","pt":"i","n":"Fabax Ltd","no":"16435704","t":"Stoke-On-Trent","i":"ecommerce","in":"Online Retail & E-commerce","r":"west-midlands","rn":"West Midlands"},{"pn":"Mr Vincent Uchegbu","pt":"i","n":"Ltz Pharma Ltd","no":"11299513","t":"Dronfield","i":"ecommerce","in":"Online Retail & E-commerce","r":"yorkshire","rn":"Yorkshire & Humber"},{"pn":"Mr Alperen Ucar","pt":"i","n":"Nexoraise Ltd","no":"16989382","t":"London","i":"electrical","in":"Electrical Services","r":"london","rn":"London"},{"pn":"Mr Paul-Florin Ucrainet","pt":"i","n":"Daniel Cdi Services Ltd","no":"13099014","t":"London","i":"electrical","in":"Electrical Services","r":"london","rn":"London"},{"pn":"Mrs Raminta Uchuvatova","pt":"i","n":"Capital Electrical And Building Contractors Ltd","no":"11140473","t":"South Croydon","i":"electrical","in":"Electrical Services","r":"london","rn":"London"},{"pn":"Mr Pawel Uczciwek","pt":"i","n":"Xenergy Ltd","no":"13962747","t":"London","i":"electrical","in":"Electrical Services","r":"london","rn":"London"},{"pn":"Mr Oleksandr Uchuvatov","pt":"i","n":"Capital Electrical Contractor Limited","no":"06786302","t":"South Croydon","i":"electrical","in":"Electrical Services","r":"london","rn":"London"},{"pn":"Mr Metin Uckul","pt":"i","n":"Uckul Ltd","no":"13031505","t":"Aylesford","i":"electrical","in":"Electrical Services","r":"south-east","rn":"South East England"},{"pn":"Iheanyi Benjamin Uchendu","pt":"i","n":"Jamin Medicals Limited","no":"16018308","t":"Harlow","i":"healthcare","in":"Healthcare Services","r":"east-england","rn":"East of England"},{"pn":"Kent Uche","pt":"i","n":"Diabam Children Empowerment Ltd","no":"11766396","t":"St. Albans","i":"healthcare","in":"Healthcare Services","r":"east-england","rn":"East of England"},{"pn":"Mrs Ndidi Uchenwoke","pt":"i","n":"Zhara Ltd","no":"11820974","t":"Hatfield","i":"healthcare","in":"Healthcare Services","r":"east-england","rn":"East of England"},{"pn":"Mr Ikenna Uchenwoke","pt":"i","n":"Primrose Plus Ltd","no":"07145149","t":"Hatfield","i":"healthcare","in":"Healthcare Services","r":"east-england","rn":"East of England"},{"pn":"Dr Nwamaka Uchendu","pt":"i","n":"Pavillion Care Limited","no":"06560834","t":"Manea","i":"healthcare","in":"Healthcare Services","r":"east-midlands","rn":"East Midlands"},{"pn":"Miss Ngozi Marilyn Uche-Ubochi","pt":"i","n":"Novah Healthcare Ltd","no":"14911961","t":"Northampton","i":"healthcare","in":"Healthcare Services","r":"east-midlands","rn":"East Midlands"},{"pn":"Mr Umit Ucar","pt":"i","n":"Pure Beauty Tourism Ltd","no":"12422207","t":"London","i":"healthcare","in":"Healthcare Services","r":"london","rn":"London"},{"pn":"Mr Kelechi Augustine Uchegbu","pt":"i","n":"O2 Points Limited","no":"16034026","t":"London","i":"healthcare","in":"Healthcare Services","r":"london","rn":"London"},{"pn":"Mr Charles Chikwelu Uche","pt":"i","n":"Amicharly Limited","no":"13927020","t":"London","i":"healthcare","in":"Healthcare Services","r":"london","rn":"London"},{"pn":"Mr Nnamdi Benny Chizurum Uche","pt":"i","n":"Duairo Ltd","no":"16586882","t":"London","i":"healthcare","in":"Healthcare Services","r":"london","rn":"London"},{"pn":"Mr. Jerome Uchenna","pt":"i","n":"Jergins Company Ltd","no":"15956311","t":"London","i":"healthcare","in":"Healthcare Services","r":"london","rn":"London"},{"pn":"Mrs. Ginikachukwu Uchenna","pt":"i","n":"Jergins Company Ltd","no":"15956311","t":"London","i":"healthcare","in":"Healthcare Services","r":"london","rn":"London"},{"pn":"Ms Ikbal Birsel Uckun","pt":"i","n":"Quest Holistic Therapy Ltd","no":"13399800","t":"London","i":"healthcare","in":"Healthcare Services","r":"london","rn":"London"},{"pn":"Mr Christopher Chiagozie Uchenwa","pt":"i","n":"Okar Ltd","no":"16011530","t":"London","i":"healthcare","in":"Healthcare Services","r":"london","rn":"London"},{"pn":"Mrs Nana Palm Uchenna","pt":"i","n":"Unique Health Trust Ltd","no":"06562422","t":"London","i":"healthcare","in":"Healthcare Services","r":"london","rn":"London"},{"pn":"Mr Valerio Uccellani","pt":"i","n":"Health Screening Lab Ltd","no":"15271831","t":"London","i":"healthcare","in":"Healthcare Services","r":"london","rn":"London"},{"pn":"Ikechukwu Uchendu","pt":"i","n":"Morlink Ltd","no":"13902231","t":"Mitcham","i":"healthcare","in":"Healthcare Services","r":"london","rn":"London"},{"pn":"Mrs Ijeoma Ogechi Uchendu","pt":"i","n":"T'Sure Healthcare Ltd","no":"16435133","t":"London","i":"healthcare","in":"Healthcare Services","r":"london","rn":"London"},{"pn":"Sevinc Ucar","pt":"i","n":"Antorion Tourism Travel Agency Ltd","no":"14088009","t":"London","i":"healthcare","in":"Healthcare Services","r":"london","rn":"London"},{"pn":"Mrs Ihuoma Edith Uche","pt":"i","n":"Open Gates Target Ltd","no":"14462042","t":"Thornton Heath","i":"healthcare","in":"Healthcare Services","r":"london","rn":"London"},{"pn":"Dr Edvige Uccelli","pt":"i","n":"The Headland Clinic Ltd","no":"05127122","t":"Hartlepool","i":"healthcare","in":"Healthcare Services","r":"north-east","rn":"North East England"},{"pn":"Ms Eleanor Oluchi Uchewuakor","pt":"i","n":"Aurora Alpha Limited","no":"12976944","t":"Manchester","i":"healthcare","in":"Healthcare Services","r":"north-west","rn":"North West England"},{"pn":"Mr Dennis Pascal Uche","pt":"i","n":"Dennis Pascal Uche Limited","no":"08942822","t":"Manchester","i":"healthcare","in":"Healthcare Services","r":"north-west","rn":"North West England"},{"pn":"Gloria Ngozi Itoro Uchegbulam","pt":"i","n":"Glofitness Community Cic","no":"15491162","t":"Heywood","i":"healthcare","in":"Healthcare Services","r":"north-west","rn":"North West England"},{"pn":"Dr Chukwuemeka Dubem Uchendu","pt":"i","n":"Holistikia Services Ltd","no":"SC863919","t":"Dundee","i":"healthcare","in":"Healthcare Services","r":"scotland","rn":"Scotland"},{"pn":"Ifeanyi Julius Ucha","pt":"i","n":"Civi Tas Dei Healthcare Ltd","no":"15846704","t":"Canterbury","i":"healthcare","in":"Healthcare Services","r":"south-east","rn":"South East England"},{"pn":"Mr Ndubuisi Nelson Uche-Idam","pt":"i","n":"Rehoboth Group Of Company Ltd","no":"14045276","t":"Southampton","i":"healthcare","in":"Healthcare Services","r":"south-east","rn":"South East England"},{"pn":"Dr Chioma Uche","pt":"i","n":"Chi4G Limited","no":"07944866","t":"Maidstone","i":"healthcare","in":"Healthcare Services","r":"south-east","rn":"South East England"},{"pn":"Dr Nicole Uchenna Uchendu","pt":"i","n":"Blose Medical Ltd","no":"14571214","t":"Westerham","i":"healthcare","in":"Healthcare Services","r":"south-east","rn":"South East England"},{"pn":"Mr Emmanuel Chukwudi Uchedike","pt":"i","n":"Emacist Limited","no":"09367007","t":"Bristol","i":"healthcare","in":"Healthcare Services","r":"south-west","rn":"South West England"},{"pn":"Mr Eric Ginikachi Uchenna","pt":"i","n":"Kachyrik Limited","no":"15131543","t":"Bristol","i":"healthcare","in":"Healthcare Services","r":"south-west","rn":"South West England"},{"pn":"Dr Mario Uccello","pt":"i","n":"Mario7 Ltd","no":"12254176","t":"Bath","i":"healthcare","in":"Healthcare Services","r":"south-west","rn":"South West England"},{"pn":"Mrs Emilia Ukamaka Uchedike","pt":"i","n":"Emiliaz Limited","no":"09244408","t":"Bristol","i":"healthcare","in":"Healthcare Services","r":"south-west","rn":"South West England"},{"pn":"Mr Chigozie Akobundu Uchegbulam","pt":"i","n":"Chibest Services Ltd","no":"16725667","t":"Cardiff","i":"healthcare","in":"Healthcare Services","r":"wales","rn":"Wales"},{"pn":"Mr Ogbonnaya Jonah Ucheh","pt":"i","n":"Jonah Care Ltd","no":"14453536","t":"Birmingham","i":"healthcare","in":"Healthcare Services","r":"west-midlands","rn":"West Midlands"},{"pn":"Ms Joy Imante Uchidiuno","pt":"i","n":"Imamedic  Care Ltd","no":"13875667","t":"Telford","i":"healthcare","in":"Healthcare Services","r":"west-midlands","rn":"West Midlands"},{"pn":"Mrs Ifeyinwa Jovita Uchenna","pt":"i","n":"Kairos Health Limited","no":"17048139","t":"Birmingham","i":"healthcare","in":"Healthcare Services","r":"west-midlands","rn":"West Midlands"},{"pn":"Manjima Uchambally","pt":"i","n":"Vitazeal Healthcare Ltd","no":"16144237","t":"Rotherham","i":"healthcare","in":"Healthcare Services","r":"yorkshire","rn":"Yorkshire & Humber"},{"pn":"Chidiebere Veronica Uche-Ekwere","pt":"i","n":"Goretti Medical Services Ltd","no":"16591244","t":"Leeds","i":"healthcare","in":"Healthcare Services","r":"yorkshire","rn":"Yorkshire & Humber"},{"pn":"Stella Maria E Eberechukwa Ucheobi","pt":"i","n":"Anthony Saint Ltd","no":"16439959","t":"Bury St. Edmunds","i":"hotels","in":"Hotels & Accommodation","r":"east-england","rn":"East of England"},{"pn":"Mr Anayo Afam Uche","pt":"i","n":"Transformative Housing Cic","no":"14741960","t":"Nottingham","i":"hotels","in":"Hotels & Accommodation","r":"east-midlands","rn":"East Midlands"},{"pn":"Mr Mazlum Ucar","pt":"i","n":"Chequers Smart Stays Ltd","no":"16888153","t":"London","i":"hotels","in":"Hotels & Accommodation","r":"london","rn":"London"},{"pn":"Dr Chidiebere Uche","pt":"i","n":"Modern Shortlets Limited","no":"11487125","t":"Kidlington","i":"hotels","in":"Hotels & Accommodation","r":"south-east","rn":"South East England"},{"pn":"Mrs Grace Uche","pt":"i","n":"Modern Shortlets Limited","no":"11487125","t":"Kidlington","i":"hotels","in":"Hotels & Accommodation","r":"south-east","rn":"South East England"},{"pn":"Dr Chidiebere Uche","pt":"i","n":"Miniyap Consultancy Limited","no":"08017554","t":"Kidlington","i":"hotels","in":"Hotels & Accommodation","r":"south-east","rn":"South East England"},{"pn":"Mrs Grace Uche","pt":"i","n":"Miniyap Consultancy Limited","no":"08017554","t":"Kidlington","i":"hotels","in":"Hotels & Accommodation","r":"south-east","rn":"South East England"},{"pn":"Ms Uchenna Ifeyinwa Uchegbu","pt":"i","n":"Jaykay It Solutions Limited","no":"11909865","t":"Harlow","i":"it-consulting","in":"IT Consulting","r":"east-england","rn":"East of England"},{"pn":"Mr Emeka Uchendi","pt":"i","n":"Itwize Technology Uk Limited","no":"15401316","t":"Nottingham","i":"it-consulting","in":"IT Consulting","r":"east-midlands","rn":"East Midlands"},{"pn":"Mr Sait Ucar","pt":"i","n":"Saap Ltd","no":"12539811","t":"London","i":"it-consulting","in":"IT Consulting","r":"london","rn":"London"},{"pn":"Mr Mehmet Burak Ucakan","pt":"i","n":"Drivingo Ai Ltd","no":"16336490","t":"London","i":"it-consulting","in":"IT Consulting","r":"london","rn":"London"},{"pn":"Mr Ohuku Uche","pt":"i","n":"Theuches Ltd","no":"11373431","t":"Croydon","i":"it-consulting","in":"IT Consulting","r":"london","rn":"London"},{"pn":"Mr Edwin Ugwu Uche","pt":"i","n":"Your Enterprise Served Limited","no":"04514961","t":"Thornton Heath","i":"it-consulting","in":"IT Consulting","r":"london","rn":"London"},{"pn":"Ms Ayaka Uchida","pt":"i","n":"A-Digital Works Ltd","no":"15081203","t":"London","i":"it-consulting","in":"IT Consulting","r":"london","rn":"London"},{"pn":"Mr Chima Daniel Uchechi","pt":"i","n":"Delatah Ltd","no":"13514333","t":"Longfield","i":"it-consulting","in":"IT Consulting","r":"london","rn":"London"},{"pn":"Mr Senol Ucpinar","pt":"i","n":"Blue Software Solutions Ltd","no":"12509109","t":"London","i":"it-consulting","in":"IT Consulting","r":"london","rn":"London"},{"pn":"Mr Ahmet Ucar","pt":"i","n":"Grc Plus Ltd","no":"13664716","t":"London","i":"it-consulting","in":"IT Consulting","r":"london","rn":"London"},{"pn":"Mr Mehmet Burak Ucakan","pt":"i","n":"Sosimple Digital Ltd","no":"10164358","t":"London","i":"it-consulting","in":"IT Consulting","r":"london","rn":"London"},{"pn":"Mr Chinonso Uche","pt":"i","n":"Pearest Ltd","no":"16758734","t":"Liverpool","i":"it-consulting","in":"IT Consulting","r":"north-west","rn":"North West England"},{"pn":"Mr David Guy Uccelli","pt":"i","n":"Agile Commerce Group Ltd.","no":"03833636","t":"Petersfield","i":"it-consulting","in":"IT Consulting","r":"south-east","rn":"South East England"},{"pn":"Mr Uchenna Chiemeka Jnr Uche-Ejiogu","pt":"i","n":"Xoro Consultancy Ltd","no":"13280354","t":"Aldershot","i":"it-consulting","in":"IT Consulting","r":"south-east","rn":"South East England"},{"pn":"Mr Nnaemeka Uchenna-Emezue","pt":"i","n":"Shadowbriar Solutions Limited","no":"09496985","t":"Guildford","i":"it-consulting","in":"IT Consulting","r":"south-east","rn":"South East England"},{"pn":"Mr Mustafa Ucar","pt":"i","n":"Ucar Technology Limited","no":"15997567","t":"Cardiff","i":"it-consulting","in":"IT Consulting","r":"wales","rn":"Wales"},{"pn":"Mr Uchenna Martin Uchendu","pt":"i","n":"Zaintec Ltd","no":"16852139","t":"Stoke-On-Trent","i":"it-consulting","in":"IT Consulting","r":"west-midlands","rn":"West Midlands"},{"pn":"Mr Praise Chukwuemeka Uche","pt":"i","n":"Amarik Financial Tech Ltd","no":"16947517","t":"Birmingham","i":"it-consulting","in":"IT Consulting","r":"west-midlands","rn":"West Midlands"},{"pn":"Mr Kayra Uckilinc","pt":"i","n":"Key And Board Limited","no":"16870189","t":"London","i":"it-services","in":"IT Services & Support","r":"london","rn":"London"},{"pn":"Mr Hakki Ucar","pt":"i","n":"Rakipsiz Ltd","no":"16755751","t":"London","i":"it-services","in":"IT Services & Support","r":"london","rn":"London"},{"pn":"Mr Muhammet Enes Ucar","pt":"i","n":"Esc Hub Ltd","no":"16356124","t":"London","i":"it-services","in":"IT Services & Support","r":"london","rn":"London"},{"pn":"Ms Ceyda Ucyigit","pt":"i","n":"Bee Legal Limited","no":"13582439","t":"West Wickham","i":"legal","in":"Legal Services","r":"london","rn":"London"},{"pn":"Mr Ozcan Ucaroglu","pt":"i","n":"Robin Kendall And Co Limited","no":"11820601","t":"Enfield","i":"legal","in":"Legal Services","r":"london","rn":"London"},{"pn":"Mr Junji Uchiyama","pt":"i","n":"Forus Global Law Firm Ltd","no":"14698972","t":"London","i":"legal","in":"Legal Services","r":"london","rn":"London"},{"pn":"Mr Sebastian Uckermann","pt":"i","n":"Kenston Business London Ltd","no":"15498194","t":"Brentwood","i":"management-consulting","in":"Management Consultancy","r":"east-england","rn":"East of England"},{"pn":"Mr Kemal Ucar","pt":"i","n":"Kemosabe35 Limited","no":"16905296","t":"Epping","i":"management-consulting","in":"Management Consultancy","r":"east-england","rn":"East of England"},{"pn":"Miss Berna Suzan Ucel","pt":"i","n":"Mih Major Events Ltd","no":"14383573","t":"Towcester","i":"management-consulting","in":"Management Consultancy","r":"east-midlands","rn":"East Midlands"},{"pn":"Miss Berna Suzan Ucel","pt":"i","n":"Berna Ltd","no":"14787561","t":"Towcester","i":"management-consulting","in":"Management Consultancy","r":"east-midlands","rn":"East Midlands"},{"pn":"Mr Ufuk Ucar","pt":"i","n":"Lighton Lighting Ltd","no":"15235342","t":"London","i":"management-consulting","in":"Management Consultancy","r":"london","rn":"London"},{"pn":"Mr Erhan Uckun","pt":"i","n":"Dormek Ltd","no":"11842608","t":"London","i":"management-consulting","in":"Management Consultancy","r":"london","rn":"London"},{"pn":"Miss Dilek Ucar","pt":"i","n":"Venus Beauty & Esthetic Ltd","no":"12061815","t":"London","i":"management-consulting","in":"Management Consultancy","r":"london","rn":"London"},{"pn":"Miss Nalan Ucar","pt":"i","n":"Ruvece Counselling Ltd","no":"15508841","t":"London","i":"management-consulting","in":"Management Consultancy","r":"london","rn":"London"},{"pn":"Mr Titus Chikodili Uchem","pt":"i","n":"Tychichem Ltd","no":"11892341","t":"Dagenham","i":"management-consulting","in":"Management Consultancy","r":"london","rn":"London"},{"pn":"Mr Sergio Monteiro Uchôa","pt":"i","n":"Uchoa Capital Group Uk Ltd","no":"16392566","t":"London","i":"management-consulting","in":"Management Consultancy","r":"london","rn":"London"},{"pn":"Luca Matumoto Monteiro Uchoa","pt":"i","n":"Uchoa Capital Group Uk Ltd","no":"16392566","t":"London","i":"management-consulting","in":"Management Consultancy","r":"london","rn":"London"},{"pn":"Ms Sibel Ucur","pt":"i","n":"Sida Health And Beauty Ltd","no":"11883423","t":"London","i":"management-consulting","in":"Management Consultancy","r":"london","rn":"London"},{"pn":"Santosh Sanjiva Uchil","pt":"i","n":"Euro Assessments & Certification Ltd","no":"11822437","t":"London","i":"management-consulting","in":"Management Consultancy","r":"london","rn":"London"},{"pn":"Mr Hiroki Uchimoto","pt":"i","n":"Yuen Yeung Ltd","no":"14100425","t":"London","i":"management-consulting","in":"Management Consultancy","r":"london","rn":"London"},{"pn":"Mr Cengiz Ferhat Ucbasaran","pt":"i","n":"Exploreye Consulting Limited","no":"10558169","t":"Palmers Green","i":"management-consulting","in":"Management Consultancy","r":"london","rn":"London"},{"pn":"Mr Pawel Uczciwek","pt":"i","n":"Pawel Asif Design Ltd","no":"11004544","t":"Southall","i":"management-consulting","in":"Management Consultancy","r":"london","rn":"London"},{"pn":"Ms Gizem Ucar","pt":"i","n":"Nartio Limited","no":"14714891","t":"London","i":"management-consulting","in":"Management Consultancy","r":"london","rn":"London"},{"pn":"Serdar Sinan Ucanlar","pt":"i","n":"Atmaca Uk Logistics Ltd","no":"11239160","t":"London","i":"management-consulting","in":"Management Consultancy","r":"london","rn":"London"},{"pn":"Mr Ufuk Ucar","pt":"i","n":"Qlegal Ltd","no":"12089329","t":"London","i":"management-consulting","in":"Management Consultancy","r":"london","rn":"London"},{"pn":"Mr Umit Ucar","pt":"i","n":"Emt Uk Investment Ltd","no":"16365077","t":"London","i":"management-consulting","in":"Management Consultancy","r":"london","rn":"London"},{"pn":"Ms Esra Ucar","pt":"i","n":"Emt Uk Investment Ltd","no":"16365077","t":"London","i":"management-consulting","in":"Management Consultancy","r":"london","rn":"London"},{"pn":"Mr Ufuk Ucar","pt":"i","n":"Medhera Health Limited","no":"15324092","t":"London","i":"management-consulting","in":"Management Consultancy","r":"london","rn":"London"},{"pn":"Mr Nevzat Ucar","pt":"i","n":"Ideal Localization And Consulting Ltd","no":"13311944","t":"London","i":"management-consulting","in":"Management Consultancy","r":"london","rn":"London"},{"pn":"Mr Ufuk Ucar","pt":"i","n":"Dorniz Fashion & Beauty Ltd","no":"15537195","t":"London","i":"management-consulting","in":"Management Consultancy","r":"london","rn":"London"},{"pn":"Ms Duygu Saracoglu Ucak","pt":"i","n":"Doras Consultancy Ltd","no":"12490726","t":"London","i":"management-consulting","in":"Management Consultancy","r":"london","rn":"London"},{"pn":"Mr Jose Luis Ucar","pt":"i","n":"Jose Ucar Ltd","no":"14807486","t":"North Shields","i":"management-consulting","in":"Management Consultancy","r":"north-east","rn":"North East England"},{"pn":"Mr Maksymilian Uciechowski","pt":"i","n":"Solus Max Ltd","no":"16404571","t":"Preston","i":"management-consulting","in":"Management Consultancy","r":"north-west","rn":"North West England"},{"pn":"Mr Ezeala Ofehegbu Uchegbu","pt":"i","n":"Bpes Consultancy Ltd","no":"16975060","t":"Liverpool","i":"management-consulting","in":"Management Consultancy","r":"north-west","rn":"North West England"},{"pn":"Mr Kedu Odimna Uchegbu","pt":"i","n":"Black Panther Ent Ltd","no":"15409204","t":"Liverpool","i":"management-consulting","in":"Management Consultancy","r":"north-west","rn":"North West England"},{"pn":"Mr Fabian Andres Correa Uchima","pt":"i","n":"Progressive Patterns Ltd","no":"13958731","t":"Liverpool","i":"management-consulting","in":"Management Consultancy","r":"north-west","rn":"North West England"},{"pn":"Miss Ijeoma Ogechi Uchendu","pt":"i","n":"Lightcn Consultancy Services Ltd","no":"10539424","t":"Sandwich","i":"management-consulting","in":"Management Consultancy","r":"south-east","rn":"South East England"},{"pn":"Miss Ijeoma Ogechi Uchendu","pt":"i","n":"Lightcn Global Services Ltd","no":"08529891","t":"Sandwich","i":"management-consulting","in":"Management Consultancy","r":"south-east","rn":"South East England"},{"pn":"Mr Kelvin Emeka Uchemefune","pt":"i","n":"Kelvin Inspires Ltd","no":"12386105","t":"Fareham","i":"management-consulting","in":"Management Consultancy","r":"south-east","rn":"South East England"},{"pn":"Mr Andrew Uche","pt":"i","n":"Andrew Ouche Consult Ltd","no":"13546565","t":"Dudley","i":"management-consulting","in":"Management Consultancy","r":"west-midlands","rn":"West Midlands"},{"pn":"Robert Uckerman","pt":"i","n":"Kelvington Development Limited","no":"07591275","t":"Oswestry","i":"management-consulting","in":"Management Consultancy","r":"yorkshire","rn":"Yorkshire & Humber"},{"pn":"Mr Richmond Uchebraye","pt":"i","n":"Agolo Metal Work Ltd","no":"16811241","t":"Wigan","i":"manufacturing","in":"Manufacturing & Fabrication","r":"north-west","rn":"North West England"},{"pn":"Miss Precious Amarachukwu Okoye Uchechukwu","pt":"i","n":"The Noire Space Cic","no":"14373515","t":"Mitcham","i":"marketing","in":"Marketing & Advertising","r":"london","rn":"London"},{"pn":"Mr Micah Uche","pt":"i","n":"Regal North Ltd","no":"16195104","t":"London","i":"marketing","in":"Marketing & Advertising","r":"london","rn":"London"},{"pn":"Mr Nicolae Uciu","pt":"i","n":"Ads And More Ltd","no":"13341426","t":"London","i":"marketing","in":"Marketing & Advertising","r":"london","rn":"London"},{"pn":"Mr Osman Ucar","pt":"i","n":"Host Osiris Ltd","no":"16557749","t":"London","i":"marketing","in":"Marketing & Advertising","r":"london","rn":"London"},{"pn":"Mr Ivan Uchanov","pt":"i","n":"Vivamedia Solutions Limited","no":"15296294","t":"Littlehampton","i":"marketing","in":"Marketing & Advertising","r":"south-east","rn":"South East England"},{"pn":"Hakan Ucar","pt":"i","n":"Hakan Leaflet Distribution Ltd","no":"13567666","t":"Dronfield","i":"marketing","in":"Marketing & Advertising","r":"yorkshire","rn":"Yorkshire & Humber"},{"pn":"Mr Ahmet Ucar","pt":"i","n":"Budget Handyman & Plumbing Services Ltd","no":"13015852","t":"London","i":"plumbing","in":"Plumbing & Heating","r":"london","rn":"London"},{"pn":"Miss Mine Ucgun","pt":"i","n":"Likapa Digital Ltd","no":"13033830","t":"Hove","i":"pr","in":"PR & Communications","r":"south-east","rn":"South East England"},{"pn":"Mr Edwin Ugwu Uche","pt":"i","n":"111 Ecclesbourne Road Management Company Ltd","no":"10620321","t":"Thornton Heath","i":"property-management","in":"Property Management","r":"london","rn":"London"},{"pn":"Mr Javier Collado Ucher","pt":"i","n":"Fenix Rentals Limited","no":"12802360","t":"London","i":"property-management","in":"Property Management","r":"london","rn":"London"},{"pn":"Mr Kemal Ucur","pt":"i","n":"Tfc Palmers Green Limited","no":"06713083","t":"London","i":"property-management","in":"Property Management","r":"london","rn":"London"},{"pn":"Dr Edvige Uccelli","pt":"i","n":"Headland Property Management Ltd","no":"06448150","t":"Gateshead","i":"property-management","in":"Property Management","r":"north-east","rn":"North East England"},{"pn":"Mr Halil Uchyigit","pt":"i","n":"Regency Property Management Services Ltd","no":"11793493","t":"Eastbourne","i":"property-management","in":"Property Management","r":"south-east","rn":"South East England"},{"pn":"Ms Mine Uchyigit","pt":"i","n":"Regency Property Management Services Ltd","no":"11793493","t":"Eastbourne","i":"property-management","in":"Property Management","r":"south-east","rn":"South East England"},{"pn":"Mr Yusuf Uckardes","pt":"i","n":"Ysf3 Limited","no":"16703040","t":"Sevenoaks","i":"property-management","in":"Property Management","r":"south-east","rn":"South East England"},{"pn":"Mr Mert Uckardes","pt":"i","n":"Ysf3 Limited","no":"16703040","t":"Sevenoaks","i":"property-management","in":"Property Management","r":"south-east","rn":"South East England"},{"pn":"Mr Ufuk Ucar","pt":"i","n":"Nis Investmend Ltd","no":"15507936","t":"Milton Keynes","i":"property","in":"Property & Real Estate","r":"east-midlands","rn":"East Midlands"},{"pn":"Mrs Jaymini Uchil","pt":"i","n":"Relaro Ltd","no":"11550908","t":"Coventry","i":"property","in":"Property & Real Estate","r":"east-midlands","rn":"East Midlands"},{"pn":"Eugene Uche","pt":"i","n":"St. Anderson Consultancy Limited","no":"12431975","t":"Bexleyheath","i":"property","in":"Property & Real Estate","r":"london","rn":"London"},{"pn":"Dr Ogugua Chile Uchechukwu","pt":"i","n":"Spica Properties Limited","no":"16678783","t":"Gravesend","i":"property","in":"Property & Real Estate","r":"london","rn":"London"},{"pn":"Mrs Esin Ucar","pt":"i","n":"Lighthaus Properties Ltd","no":"12019020","t":"London","i":"property","in":"Property & Real Estate","r":"london","rn":"London"},{"pn":"Mr Edison Uci","pt":"i","n":"Quiet Properties Ltd","no":"14762019","t":"London","i":"property","in":"Property & Real Estate","r":"london","rn":"London"},{"pn":"Miss Chidi Uchendu","pt":"i","n":"Prudence Property Management Ltd","no":"16210651","t":"London","i":"property","in":"Property & Real Estate","r":"london","rn":"London"},{"pn":"Houseyin Burak Uchar","pt":"i","n":"Eden Partner Properties Ltd","no":"14253606","t":"London","i":"property","in":"Property & Real Estate","r":"london","rn":"London"},{"pn":"Dr Gunen Ucyigit","pt":"i","n":"Coskunsu Limited","no":"11787812","t":"West Wickham","i":"property","in":"Property & Real Estate","r":"london","rn":"London"},{"pn":"Ms Damla Ucak","pt":"i","n":"Aymir Limited","no":"14316381","t":"Enfield","i":"property","in":"Property & Real Estate","r":"london","rn":"London"},{"pn":"Mr Huseyin Ucur","pt":"i","n":"Marco Estates Limited","no":"13092027","t":"London","i":"property","in":"Property & Real Estate","r":"london","rn":"London"},{"pn":"Cengiz Ucar","pt":"i","n":"Homes R Us Development Limited","no":"13520245","t":"Loughton","i":"property","in":"Property & Real Estate","r":"london","rn":"London"},{"pn":"Mr Houseyin Burak Uchar","pt":"i","n":"Uchar Property Limited","no":"14430898","t":"London","i":"property","in":"Property & Real Estate","r":"london","rn":"London"},{"pn":"Mrs Esin Ucar","pt":"i","n":"Uchar Property Limited","no":"14430898","t":"London","i":"property","in":"Property & Real Estate","r":"london","rn":"London"},{"pn":"Mr Baran Ucku","pt":"i","n":"Burproperties Ltd","no":"15577712","t":"London","i":"property","in":"Property & Real Estate","r":"london","rn":"London"},{"pn":"Mr Edwin Ugwu Uche","pt":"i","n":"Trio Property Management Ltd","no":"12320470","t":"London","i":"property","in":"Property & Real Estate","r":"london","rn":"London"},{"pn":"Mr Ihemelandu Josiah Uche","pt":"i","n":"First Asset Management Ltd","no":"16258699","t":"London","i":"property","in":"Property & Real Estate","r":"london","rn":"London"},{"pn":"Mr Javier Collado Ucher","pt":"i","n":"Smart Inversiones Ltd","no":"14302420","t":"London","i":"property","in":"Property & Real Estate","r":"london","rn":"London"},{"pn":"Mr Tayfun Ucar","pt":"i","n":"Ucar Property Ltd","no":"16789182","t":"London","i":"property","in":"Property & Real Estate","r":"london","rn":"London"},{"pn":"Ms Saniye Ucku","pt":"i","n":"Bbsm Investments Ltd","no":"14543642","t":"London","i":"property","in":"Property & Real Estate","r":"london","rn":"London"},{"pn":"Mr Baran Can Ucku","pt":"i","n":"Bbsm Investments Ltd","no":"14543642","t":"London","i":"property","in":"Property & Real Estate","r":"london","rn":"London"},{"pn":"Mr Salman Ucer","pt":"i","n":"Beamonds Investment Ltd","no":"13978094","t":"London","i":"property","in":"Property & Real Estate","r":"london","rn":"London"},{"pn":"Mrs Ifeyinwa Cordelia Uchendu","pt":"i","n":"Cordelmay Ltd","no":"14665618","t":"London","i":"property","in":"Property & Real Estate","r":"london","rn":"London"},{"pn":"Mr Edwin Ugwu Uche","pt":"i","n":"Cornerstone Providence Ltd","no":"16644378","t":"London","i":"property","in":"Property & Real Estate","r":"london","rn":"London"},{"pn":"Mrs Ihuoma Edith Uche","pt":"i","n":"Cornerstone Providence Ltd","no":"16644378","t":"London","i":"property","in":"Property & Real Estate","r":"london","rn":"London"},{"pn":"Miss Asli Salih Ucyigit","pt":"i","n":"Serasli Limited","no":"11939259","t":"West Wickham","i":"property","in":"Property & Real Estate","r":"london","rn":"London"},{"pn":"Miss Serife Ucur","pt":"i","n":"The Mooving Property Limited","no":"11668125","t":"London","i":"property","in":"Property & Real Estate","r":"london","rn":"London"},{"pn":"Mr Mazlum Ucar","pt":"i","n":"Ucar Porperties Limited","no":"16839682","t":"London","i":"property","in":"Property & Real Estate","r":"london","rn":"London"},{"pn":"Mr Dogan Ucar","pt":"i","n":"Arel Properties Ltd","no":"14922074","t":"London","i":"property","in":"Property & Real Estate","r":"london","rn":"London"},{"pn":"Mr Prince Uche","pt":"i","n":"Alpha Step Links Int Ltd","no":"15624008","t":"Ruislip,","i":"property","in":"Property & Real Estate","r":"london","rn":"London"},{"pn":"Mrs Evelyn Obioma Uche","pt":"i","n":"Alpha Step Links Int Ltd","no":"15624008","t":"Ruislip,","i":"property","in":"Property & Real Estate","r":"london","rn":"London"},{"pn":"Mr Kemal Ucur","pt":"i","n":"Tfc Tottenham Limited","no":"04026726","t":"London","i":"property","in":"Property & Real Estate","r":"london","rn":"London"},{"pn":"Mr Benjamin Mustafa Ucler","pt":"i","n":"Ucr Trading Limited","no":"13893846","t":"London","i":"property","in":"Property & Real Estate","r":"london","rn":"London"},{"pn":"Mr Aziz Ucur","pt":"i","n":"Ds Plastic Bag Limited","no":"13600338","t":"London","i":"property","in":"Property & Real Estate","r":"london","rn":"London"},{"pn":"Mrs Evelyn Obioma Uche","pt":"i","n":"Angystine Properties Ltd","no":"16055861","t":"Ruislip,","i":"property","in":"Property & Real Estate","r":"london","rn":"London"},{"pn":"Mrs Diana Uchendu-Anasiudu","pt":"i","n":"De-Reg Limited","no":"13431274","t":"Erith","i":"property","in":"Property & Real Estate","r":"london","rn":"London"},{"pn":"Mrs Lilian Uche-Ekelaka","pt":"i","n":"Ul Renax Limited","no":"14867850","t":"Manchester","i":"property","in":"Property & Real Estate","r":"north-west","rn":"North West England"},{"pn":"Mr Henry Chidebere Uche","pt":"i","n":"Lery Resources Limited","no":"14788225","t":"Birkenhead","i":"property","in":"Property & Real Estate","r":"north-west","rn":"North West England"},{"pn":"Mr Erdal Ucar","pt":"i","n":"Ue Property Ltd","no":"16350070","t":"Brighton","i":"property","in":"Property & Real Estate","r":"south-east","rn":"South East England"},{"pn":"Mr Obumneme Eric Uchendu","pt":"i","n":"Joffa Limited","no":"15018380","t":"Reading","i":"property","in":"Property & Real Estate","r":"south-east","rn":"South East England"},{"pn":"Mr Obumneme Eric Uchendu","pt":"i","n":"Erijay Ltd","no":"14946264","t":"Reading","i":"property","in":"Property & Real Estate","r":"south-east","rn":"South East England"},{"pn":"Ms Mine Uchyigit","pt":"i","n":"East Sussex Property Investment Ltd","no":"16446369","t":"Eastbourne","i":"property","in":"Property & Real Estate","r":"south-east","rn":"South East England"},{"pn":"Dr Gulden Uchyigit","pt":"i","n":"East Sussex Property Investment Ltd","no":"16446369","t":"Eastbourne","i":"property","in":"Property & Real Estate","r":"south-east","rn":"South East England"},{"pn":"Halil Uchyigit","pt":"i","n":"East Sussex Property Investment Ltd","no":"16446369","t":"Eastbourne","i":"property","in":"Property & Real Estate","r":"south-east","rn":"South East England"},{"pn":"Halil Uchyigit","pt":"i","n":"East Sussex Property Management Services Ltd","no":"16447723","t":"Eastbourne","i":"property","in":"Property & Real Estate","r":"south-east","rn":"South East England"},{"pn":"Dr Gulden Uchyigit","pt":"i","n":"East Sussex Property Management Services Ltd","no":"16447723","t":"Eastbourne","i":"property","in":"Property & Real Estate","r":"south-east","rn":"South East England"},{"pn":"Ms Mine Uchyigit","pt":"i","n":"East Sussex Property Management Services Ltd","no":"16447723","t":"Eastbourne","i":"property","in":"Property & Real Estate","r":"south-east","rn":"South East England"},{"pn":"Mr Ali Ihsan Ucar","pt":"i","n":"Community Led Property Limited","no":"11629379","t":"Bristol","i":"property","in":"Property & Real Estate","r":"south-west","rn":"South West England"},{"pn":"Mr Ali Ucar","pt":"i","n":"Ucar Estate Ltd","no":"15930531","t":"Bournemouth","i":"property","in":"Property & Real Estate","r":"south-west","rn":"South West England"},{"pn":"Mr Sunday Chinedu Uche","pt":"i","n":"Consort Gardens Property Ltd","no":"12320557","t":"Cardiff","i":"property","in":"Property & Real Estate","r":"wales","rn":"Wales"},{"pn":"Mrs Splendid Chibugom Uchechukwu","pt":"i","n":"Afrihaven Limited","no":"16720213","t":"Birmingham","i":"property","in":"Property & Real Estate","r":"west-midlands","rn":"West Midlands"},{"pn":"Mr Patrick Ikechukwu Uchidiuno","pt":"i","n":"Oakfield Integrated Property Services Limited","no":"15390270","t":"Telford","i":"property","in":"Property & Real Estate","r":"west-midlands","rn":"West Midlands"},{"pn":"Chidiebere Veronica Veronica Uche-Ekwere","pt":"i","n":"Staynest Properties Group Ltd","no":"17038935","t":"Leeds","i":"property","in":"Property & Real Estate","r":"yorkshire","rn":"Yorkshire & Humber"},{"pn":"Mr Douglas Uche-Kaine","pt":"i","n":"Construct Recruit Ltd","no":"16794955","t":"London","i":"recruitment","in":"Recruitment & Staffing","r":"london","rn":"London"},{"pn":"Mr Agu Uchenyi","pt":"i","n":"Hillight Resourcing Ltd","no":"15554797","t":"London","i":"recruitment","in":"Recruitment & Staffing","r":"london","rn":"London"},{"pn":"Mr David Tom Uche","pt":"i","n":"Leadnurs Recruitment Limited","no":"16986569","t":"Birmingham","i":"recruitment","in":"Recruitment & Staffing","r":"west-midlands","rn":"West Midlands"},{"pn":"Mr David Tom Uche","pt":"i","n":"Lead Nurse Limited","no":"17007292","t":"Birmingham","i":"recruitment","in":"Recruitment & Staffing","r":"west-midlands","rn":"West Midlands"},{"pn":"Parkwalk Advisors Ltd (Managers Of Ucef)","pt":"c","n":"8Power Limited","no":"09396640","t":"Cambridge","i":"research","in":"Research & Development","r":"east-england","rn":"East of England"},{"pn":"Ijeoma Florence Uchegbu","pt":"i","n":"Nanomerics Ltd","no":"07373043","t":"London","i":"research","in":"Research & Development","r":"london","rn":"London"},{"pn":"Mr. Selahattin Ucuzcu","pt":"i","n":"Us Engineering & Consulting Company Ltd","no":"11455222","t":"Cardiff","i":"research","in":"Research & Development","r":"wales","rn":"Wales"},{"pn":"Sevgi Uckayabasi","pt":"i","n":"Neva Ltd","no":"16420878","t":"Chelmsford","i":"restaurants","in":"Restaurants & Cafes","r":"east-england","rn":"East of England"},{"pn":"Mrs Nnenna Emmanuella Uchekalu","pt":"i","n":"E&S Innovation Limited","no":"16798823","t":"Luton","i":"restaurants","in":"Restaurants & Cafes","r":"east-england","rn":"East of England"},{"pn":"Faik Ucar","pt":"i","n":"Ucar 58 Limited","no":"16309035","t":"Dereham","i":"restaurants","in":"Restaurants & Cafes","r":"east-england","rn":"East of England"},{"pn":"Mr Kemal Ucar","pt":"i","n":"Mattcupco Ltd","no":"14095319","t":"Epping","i":"restaurants","in":"Restaurants & Cafes","r":"east-england","rn":"East of England"},{"pn":"Mr Muhammed Ucan","pt":"i","n":"Bke Angel Ltd","no":"14900680","t":"London","i":"restaurants","in":"Restaurants & Cafes","r":"london","rn":"London"},{"pn":"Mr Tayfun Ucar","pt":"i","n":"Dan Catering Ltd","no":"11274476","t":"London","i":"restaurants","in":"Restaurants & Cafes","r":"london","rn":"London"},{"pn":"Mr Hasan Ucar","pt":"i","n":"Dan Catering Ltd","no":"11274476","t":"London","i":"restaurants","in":"Restaurants & Cafes","r":"london","rn":"London"},{"pn":"Mr Ozcan Ucaroglu","pt":"i","n":"De Mezka Limited","no":"10538164","t":"London","i":"restaurants","in":"Restaurants & Cafes","r":"london","rn":"London"},{"pn":"Mr Kamil Ucaroglu","pt":"i","n":"De Mezka Limited","no":"10538164","t":"London","i":"restaurants","in":"Restaurants & Cafes","r":"london","rn":"London"},{"pn":"Mr Murat Ucar","pt":"i","n":"Kaan Fish And Chips Limited","no":"10247093","t":"Orpington","i":"restaurants","in":"Restaurants & Cafes","r":"london","rn":"London"},{"pn":"Mr Mehmet Ucer","pt":"i","n":"Nar Turkish Grill Ltd","no":"17048567","t":"Bushwood - London","i":"restaurants","in":"Restaurants & Cafes","r":"london","rn":"London"},{"pn":"Mr Sedat Ucuncuoglu","pt":"i","n":"Poppins Court Ltd","no":"15435362","t":"London","i":"restaurants","in":"Restaurants & Cafes","r":"london","rn":"London"},{"pn":"Ms Pelin Ucrak","pt":"i","n":"Orange Cafe Bistro Ltd","no":"16096490","t":"London","i":"restaurants","in":"Restaurants & Cafes","r":"london","rn":"London"},{"pn":"Mr Sercihan Yusuf Ucur","pt":"i","n":"Deroka Ltd","no":"11897434","t":"London","i":"restaurants","in":"Restaurants & Cafes","r":"london","rn":"London"},{"pn":"Mrs Alev Ucyigit","pt":"i","n":"Lodge Fish Bar Limited","no":"09693498","t":"West Wickham","i":"restaurants","in":"Restaurants & Cafes","r":"london","rn":"London"},{"pn":"Mr Ibrahim Ucer","pt":"i","n":"Ucer Cafe Limited","no":"16089690","t":"Waltham Abbey","i":"restaurants","in":"Restaurants & Cafes","r":"london","rn":"London"},{"pn":"Mr Emrah Ucer","pt":"i","n":"Ucer Cafe Limited","no":"16089690","t":"Waltham Abbey","i":"restaurants","in":"Restaurants & Cafes","r":"london","rn":"London"},{"pn":"Mr Samet Uckun","pt":"i","n":"Tudee Ltd","no":"15422260","t":"London","i":"restaurants","in":"Restaurants & Cafes","r":"london","rn":"London"},{"pn":"Erdal Ucar","pt":"i","n":"Senuk Ltd","no":"11067865","t":"London","i":"restaurants","in":"Restaurants & Cafes","r":"london","rn":"London"},{"pn":"Mr Can Ucar","pt":"i","n":"Flysons Ltd","no":"16443636","t":"London","i":"restaurants","in":"Restaurants & Cafes","r":"london","rn":"London"},{"pn":"Mr Ucar Ucur","pt":"i","n":"Flysons Ltd","no":"16443636","t":"London","i":"restaurants","in":"Restaurants & Cafes","r":"london","rn":"London"},{"pn":"Mr Arif Ucar","pt":"i","n":"Araz Lina Limited","no":"14533149","t":"London","i":"restaurants","in":"Restaurants & Cafes","r":"london","rn":"London"},{"pn":"Mrs Serpil Ucaroglu","pt":"i","n":"Trendy Brunch Limited","no":"15198450","t":"Kingston Upon Thames","i":"restaurants","in":"Restaurants & Cafes","r":"london","rn":"London"},{"pn":"Mr Huseyin Ucur","pt":"i","n":"La Fontana Catering Ltd","no":"16376418","t":"London","i":"restaurants","in":"Restaurants & Cafes","r":"london","rn":"London"},{"pn":"Mr Mazlum Ucar","pt":"i","n":"Alara Enterprises Limited","no":"16769459","t":"London","i":"restaurants","in":"Restaurants & Cafes","r":"london","rn":"London"},{"pn":"Mr Kemal Ucur","pt":"i","n":"Dara Shish & Grill Restaurant Limited","no":"15880880","t":"London","i":"restaurants","in":"Restaurants & Cafes","r":"london","rn":"London"},{"pn":"Mr Erdal Ucar","pt":"i","n":"Ekm Restaurant Ltd","no":"09670882","t":"London","i":"restaurants","in":"Restaurants & Cafes","r":"london","rn":"London"},{"pn":"Mr Mazlum Ucar","pt":"i","n":"The Chequers Turkish Grill Ltd","no":"16889470","t":"London","i":"restaurants","in":"Restaurants & Cafes","r":"london","rn":"London"},{"pn":"Mr Huseyin Adnan Ucaner","pt":"i","n":"Kayra Limited","no":"03870591","t":"","i":"restaurants","in":"Restaurants & Cafes","r":"london","rn":"London"},{"pn":"Mr Kazuya Uchida","pt":"i","n":"K Squared Capital Limited","no":"15931686","t":"London","i":"restaurants","in":"Restaurants & Cafes","r":"london","rn":"London"},{"pn":"Mr Erdal Ucar","pt":"i","n":"Fen Restaurant Ltd","no":"09670570","t":"London","i":"restaurants","in":"Restaurants & Cafes","r":"london","rn":"London"},{"pn":"Mr Sedat Ucuncuoglu","pt":"i","n":"Gangam Limited","no":"09621392","t":"London","i":"restaurants","in":"Restaurants & Cafes","r":"london","rn":"London"},{"pn":"Mr Hikmet Ucar","pt":"i","n":"Mona Food Ltd","no":"13490013","t":"London","i":"restaurants","in":"Restaurants & Cafes","r":"london","rn":"London"},{"pn":"Mr Baver Ucaman","pt":"i","n":"Preston21 Ltd","no":"14179706","t":"Preston","i":"restaurants","in":"Restaurants & Cafes","r":"north-west","rn":"North West England"},{"pn":"Ms Filiz Ucuncuoglu","pt":"i","n":"The Loft Nw Limited","no":"11679730","t":"Liverpool","i":"restaurants","in":"Restaurants & Cafes","r":"north-west","rn":"North West England"},{"pn":"Miss Paola Lorena Uccello","pt":"i","n":"D&P Food Ltd","no":"11404998","t":"Stockport","i":"restaurants","in":"Restaurants & Cafes","r":"north-west","rn":"North West England"},{"pn":"Mr. Maciej Lukasz Uchman","pt":"i","n":"Uchi Project Ltd","no":"15414043","t":"Birmingham","i":"restaurants","in":"Restaurants & Cafes","r":"west-midlands","rn":"West Midlands"},{"pn":"Omite Uchola","pt":"i","n":"Mamanka Restaurant Limited","no":"16451480","t":"Stafford","i":"restaurants","in":"Restaurants & Cafes","r":"west-midlands","rn":"West Midlands"},{"pn":"Ms Damla Ucak","pt":"i","n":"Enmur Limited","no":"13003695","t":"West Bromwich","i":"restaurants","in":"Restaurants & Cafes","r":"west-midlands","rn":"West Midlands"},{"pn":"Mr Orhan Ucar","pt":"i","n":"Dkhuk Ltd","no":"15976874","t":"Swindon","i":"restaurants","in":"Restaurants & Cafes","r":"yorkshire","rn":"Yorkshire & Humber"},{"pn":"Mr Hikmet Ucar","pt":"i","n":"Nook Cafe&Bistro Ltd","no":"16581036","t":"Melksham","i":"restaurants","in":"Restaurants & Cafes","r":"yorkshire","rn":"Yorkshire & Humber"},{"pn":"Miss Zozan Ucar","pt":"i","n":"Nook Cafe&Bistro Ltd","no":"16581036","t":"Melksham","i":"restaurants","in":"Restaurants & Cafes","r":"yorkshire","rn":"Yorkshire & Humber"},{"pn":"Mr Mustafa Ucak","pt":"i","n":"Ediz Cafe House Limited","no":"16946841","t":"Doncaster","i":"restaurants","in":"Restaurants & Cafes","r":"yorkshire","rn":"Yorkshire & Humber"},{"pn":"Mr Huseyin Ucur","pt":"i","n":"Osip Ltd","no":"10412956","t":"Chipping Ongar","i":"retail","in":"General Retail","r":"east-england","rn":"East of England"},{"pn":"Mr Dogan Ucar","pt":"i","n":"Euro Poli Limited","no":"11577381","t":"Leicester","i":"retail","in":"General Retail","r":"east-midlands","rn":"East Midlands"},{"pn":"Mr Kemal Ucur","pt":"i","n":"Tfc Palmers Green (Retail) Limited","no":"09154756","t":"London","i":"retail","in":"General Retail","r":"london","rn":"London"},{"pn":"Mr Yusuf Ucar","pt":"i","n":"Kuvars Ltd","no":"12434437","t":"Enfield","i":"retail","in":"General Retail","r":"london","rn":"London"},{"pn":"Mr Yusuf Oguz Ucur","pt":"i","n":"Tfc Edgware Supermarket Ltd","no":"12288294","t":"Edgware","i":"retail","in":"General Retail","r":"london","rn":"London"},{"pn":"Mrs Zahide Ucur","pt":"i","n":"Tfc Edgware Supermarket Ltd","no":"12288294","t":"Edgware","i":"retail","in":"General Retail","r":"london","rn":"London"},{"pn":"Ms Sevda Ucanlar","pt":"i","n":"Ihlas Uk Limited","no":"05404932","t":"Waltham Abbey","i":"retail","in":"General Retail","r":"london","rn":"London"},{"pn":"Mr Serdar Sinan Ucanlar","pt":"i","n":"Ihlas Uk Limited","no":"05404932","t":"Waltham Abbey","i":"retail","in":"General Retail","r":"london","rn":"London"},{"pn":"Mr Ercan Ucur","pt":"i","n":"Ucar Investment Ltd","no":"10394909","t":"Enfield","i":"retail","in":"General Retail","r":"london","rn":"London"},{"pn":"Mr Kemal Ucur","pt":"i","n":"Evora Retail Limited","no":"12172432","t":"London","i":"retail","in":"General Retail","r":"london","rn":"London"},{"pn":"Mr Hidir Ucar","pt":"i","n":"Ege Food & Wine Ltd","no":"11477033","t":"London","i":"retail","in":"General Retail","r":"london","rn":"London"},{"pn":"Mrs Turkan Ucur","pt":"i","n":"Tfc Catford Limited","no":"03755076","t":"London","i":"retail","in":"General Retail","r":"london","rn":"London"},{"pn":"Mr Ali Ucur","pt":"i","n":"Szampion Limited","no":"10628253","t":"Waltham Cross","i":"retail","in":"General Retail","r":"london","rn":"London"},{"pn":"Mr Huseyin Ucar","pt":"i","n":"Ucar London Ltd","no":"11212210","t":"Enfield","i":"retail","in":"General Retail","r":"london","rn":"London"},{"pn":"Mrs Yildiz Ucur","pt":"i","n":"Turkish Food Centre (Edmonton) Limited","no":"03996390","t":"Edmonton","i":"retail","in":"General Retail","r":"london","rn":"London"},{"pn":"Mr Kemal Ucur","pt":"i","n":"Turkish Food Centre (Edmonton) Limited","no":"03996390","t":"Edmonton","i":"retail","in":"General Retail","r":"london","rn":"London"},{"pn":"Mrs Turkan Ucur","pt":"i","n":"Idil Retail Limited","no":"13458389","t":"London","i":"retail","in":"General Retail","r":"london","rn":"London"},{"pn":"Dr Miracle Chinwenmeri Uche","pt":"i","n":"Tower Of Refuge Limited","no":"15207510","t":"London","i":"retail","in":"General Retail","r":"london","rn":"London"},{"pn":"Mr Ercan Ucur","pt":"i","n":"Tfc Burnt Oak Limited","no":"07153395","t":"Enfield","i":"retail","in":"General Retail","r":"london","rn":"London"},{"pn":"Mr Battal Ucar","pt":"i","n":"Aren Supermarket Ltd","no":"12145726","t":"London","i":"retail","in":"General Retail","r":"london","rn":"London"},{"pn":"Mr Mehmet Ucar","pt":"i","n":"Meba Trading Ltd","no":"16300903","t":"London","i":"retail","in":"General Retail","r":"london","rn":"London"},{"pn":"Mrs Zahide Ucur","pt":"i","n":"Tfc Waltham Cross Supermarket Ltd","no":"12858328","t":"Waltham Cross","i":"retail","in":"General Retail","r":"london","rn":"London"},{"pn":"Mr Ercan Ucur","pt":"i","n":"Efes Supermarket Ltd","no":"15616074","t":"Enfield","i":"retail","in":"General Retail","r":"london","rn":"London"},{"pn":"Mr Kemal Ucur","pt":"i","n":"Food Land (Uk) Limited","no":"06236816","t":"London","i":"retail","in":"General Retail","r":"london","rn":"London"},{"pn":"Mr Caner Ucak","pt":"i","n":"Mega Organix Limited","no":"13597254","t":"London","i":"retail","in":"General Retail","r":"london","rn":"London"},{"pn":"Mr Ali Ucur","pt":"i","n":"Ziarenka Ltd","no":"11181294","t":"Waltham Cross","i":"retail","in":"General Retail","r":"london","rn":"London"},{"pn":"Mr Solomon Chinonso Ucheka","pt":"i","n":"Pasolo Ltd","no":"16481978","t":"Sunderland","i":"retail","in":"General Retail","r":"north-east","rn":"North East England"},{"pn":"Mr Muhammed Uc","pt":"i","n":"Vera Gems Ltd","no":"13945164","t":"Manchester","i":"retail","in":"General Retail","r":"north-west","rn":"North West England"},{"pn":"Mr David Maduabuchukwu Uchendu","pt":"i","n":"Davman International Limited","no":"15743798","t":"Manchester","i":"retail","in":"General Retail","r":"north-west","rn":"North West England"},{"pn":"Mrs Elizabeth Anne Ucar","pt":"i","n":"Lmb (Sc) Ltd","no":"SC588817","t":"Kirkintilloch","i":"retail","in":"General Retail","r":"scotland","rn":"Scotland"},{"pn":"Mrs Begum Ucar","pt":"i","n":"Nott Edinburgh Ltd","no":"SC771508","t":"Edinburgh","i":"retail","in":"General Retail","r":"scotland","rn":"Scotland"},{"pn":"Mr Ivan Uchanov","pt":"i","n":"S&V Digital Strategies Ltd","no":"16019795","t":"Littlehampton","i":"retail","in":"General Retail","r":"south-east","rn":"South East England"},{"pn":"Mr Pawel Uczciwek","pt":"i","n":"Jr&P Group Ltd","no":"13611826","t":"Cardiff","i":"retail","in":"General Retail","r":"wales","rn":"Wales"},{"pn":"Mrs Chioma Ebelechukwu Ucheana","pt":"i","n":"Havina International Ltd","no":"16394331","t":"Rotherham","i":"retail","in":"General Retail","r":"yorkshire","rn":"Yorkshire & Humber"},{"pn":"Mr Douglas Uche-Kaine","pt":"i","n":"Valion Group Limited","no":"16501878","t":"London","i":"security","in":"Security Services","r":"london","rn":"London"},{"pn":"Mr Robert Uche-Kaine","pt":"i","n":"Kaine Security Ltd","no":"09934613","t":"London","i":"security","in":"Security Services","r":"london","rn":"London"},{"pn":"Mrs Michelle Uche-Kaine","pt":"i","n":"Kaine Security Ltd","no":"09934613","t":"London","i":"security","in":"Security Services","r":"london","rn":"London"},{"pn":"Mr Daniel Uccheddu","pt":"i","n":"D&L Security Ltd","no":"11832806","t":"Horley","i":"security","in":"Security Services","r":"south-east","rn":"South East England"},{"pn":"Mrs Aysegul Leyla Ucak","pt":"i","n":"Aleyla Software Ltd","no":"13422927","t":"Harpenden","i":"software","in":"Software Development","r":"east-england","rn":"East of England"},{"pn":"Mr Tolga Ucar","pt":"i","n":"Touc Limited","no":"14085331","t":"Bury St. Edmunds","i":"software","in":"Software Development","r":"east-england","rn":"East of England"},{"pn":"Mr Eren Ali Ucar","pt":"i","n":"Hydra Energy Ltd","no":"16151804","t":"London","i":"software","in":"Software Development","r":"london","rn":"London"},{"pn":"Mr Burak Ucurel","pt":"i","n":"We Are Rising Interactive Ltd.","no":"08502237","t":"Stanmore","i":"software","in":"Software Development","r":"london","rn":"London"},{"pn":"Mrs Elizabeth Uchealor","pt":"i","n":"Techlogia Consulting Limited","no":"15971867","t":"London","i":"software","in":"Software Development","r":"london","rn":"London"},{"pn":"Mr Flowers Uchealor","pt":"i","n":"Techlogia Consulting Limited","no":"15971867","t":"London","i":"software","in":"Software Development","r":"london","rn":"London"},{"pn":"Mr Fatih Mehmet Ucar","pt":"i","n":"Cooldatasoft Limited","no":"07323428","t":"London","i":"software","in":"Software Development","r":"london","rn":"London"},{"pn":"Mrs Seyma Yalcin Ucar","pt":"i","n":"Cooldatasoft Limited","no":"07323428","t":"London","i":"software","in":"Software Development","r":"london","rn":"London"},{"pn":"Mr Jakub Szymon Ucinski","pt":"i","n":"Tuitionteach Ltd","no":"11897741","t":"Mitcham","i":"software","in":"Software Development","r":"london","rn":"London"},{"pn":"Mr Recai Ucok","pt":"i","n":"Dexcook Limited","no":"16256842","t":"London","i":"software","in":"Software Development","r":"london","rn":"London"},{"pn":"Mr Elendu Uche","pt":"i","n":"Dendrix Ltd","no":"14867459","t":"London","i":"software","in":"Software Development","r":"london","rn":"London"},{"pn":"Uchenna Uchechukwu-Njoku","pt":"i","n":"Ketail Technologies Limited","no":"16080792","t":"Harrow","i":"software","in":"Software Development","r":"london","rn":"London"},{"pn":"Mr Pawel Uczciwek","pt":"i","n":"Jmx Enterprises Ltd","no":"16010945","t":"London","i":"software","in":"Software Development","r":"london","rn":"London"},{"pn":"Mr Huseyin San Ucur","pt":"i","n":"Orphic Games Ltd","no":"10855066","t":"Enfield","i":"software","in":"Software Development","r":"london","rn":"London"},{"pn":"Mr Ozan Ucar","pt":"i","n":"Keepnet Labs Ltd","no":"11047987","t":"London","i":"software","in":"Software Development","r":"london","rn":"London"},{"pn":"Mr Tolga Ucar","pt":"i","n":"Alyada Limited","no":"13058693","t":"London","i":"software","in":"Software Development","r":"london","rn":"London"},{"pn":"Mr Ramazan Ucak","pt":"i","n":"Patron Holding Software Ltd","no":"15612389","t":"London","i":"software","in":"Software Development","r":"london","rn":"London"},{"pn":"Mr Fatih Mehmet Ucar","pt":"i","n":"Agile Release Limited","no":"13237670","t":"London","i":"software","in":"Software Development","r":"london","rn":"London"},{"pn":"Victory Uchenna","pt":"i","n":"Intervoice Ai Ltd","no":"16177720","t":"Bolton","i":"software","in":"Software Development","r":"north-west","rn":"North West England"},{"pn":"Miss Chekwube Anastiasia Uchea","pt":"i","n":"Cludive Ltd","no":"14349904","t":"Liverpool","i":"software","in":"Software Development","r":"north-west","rn":"North West England"},{"pn":"Mr Emeka Uchendi","pt":"i","n":"Haibot Limited","no":"15558493","t":"Birmingham","i":"software","in":"Software Development","r":"west-midlands","rn":"West Midlands"},{"pn":"Mr Stephen Amechi Uche","pt":"i","n":"Youth Nation Soccer School Ltd","no":"12605575","t":"Richmond","i":"sports","in":"Sports & Leisure Facilities","r":"london","rn":"London"},{"pn":"Lafe Uche","pt":"i","n":"Uty Sports Academy Ltd","no":"16583006","t":"Dudley","i":"sports","in":"Sports & Leisure Facilities","r":"west-midlands","rn":"West Midlands"},{"pn":"Mr Stefan Vasilievich Uchikov","pt":"i","n":"Troins Ltd","no":"16312469","t":"London","i":"taxis","in":"Taxis & Private Hire","r":"london","rn":"London"},{"pn":"Mr Adem Uckan","pt":"i","n":"Hosh Luxury Hire Ltd","no":"16299408","t":"London","i":"taxis","in":"Taxis & Private Hire","r":"london","rn":"London"},{"pn":"Mr Kelvin Emeka Uchemefune","pt":"i","n":"Eagle Rides Ltd","no":"16053798","t":"Fareham","i":"taxis","in":"Taxis & Private Hire","r":"south-east","rn":"South East England"},{"pn":"Mr Douglas Uche-Kaine","pt":"i","n":"7 To 7 Out Of School Clubs Ltd","no":"16084582","t":"Ilford","i":"training","in":"Professional Training","r":"london","rn":"London"},{"pn":"Ms Gul Ucak","pt":"i","n":"Yap-Der Ltd","no":"15653271","t":"London","i":"training","in":"Professional Training","r":"london","rn":"London"},{"pn":"Mr Baran Ucku","pt":"i","n":"London School Of Learning Limited","no":"15624587","t":"London","i":"training","in":"Professional Training","r":"london","rn":"London"},{"pn":"Ms Caroline Uchima","pt":"i","n":"May Peace Prevail On Earth International Ltd.","no":"SC331253","t":"Dumfries","i":"training","in":"Professional Training","r":"scotland","rn":"Scotland"},{"pn":"Mrs Grace Uche","pt":"i","n":"Imperial Tech Companies Limited","no":"12981877","t":"Swindon","i":"training","in":"Professional Training","r":"yorkshire","rn":"Yorkshire & Humber"},{"pn":"Mr Hakan Ucan","pt":"i","n":"Dostlar Trans Ltd","no":"14315819","t":"Coventry","i":"transport","in":"Road Transport & Haulage","r":"east-midlands","rn":"East Midlands"},{"pn":"Mr Remigius Nnadiwuagha Uche","pt":"i","n":"Remmiget Limited","no":"13664643","t":"Derby","i":"transport","in":"Road Transport & Haulage","r":"east-midlands","rn":"East Midlands"},{"pn":"Mr Goksen Ucur","pt":"i","n":"Sila Cargo Uk Limited","no":"15967763","t":"Enfield","i":"transport","in":"Road Transport & Haulage","r":"london","rn":"London"},{"pn":"Mr Cem Kamil Ucur","pt":"i","n":"Cku Transport Ltd","no":"11662497","t":"London","i":"transport","in":"Road Transport & Haulage","r":"london","rn":"London"},{"pn":"Mr Marek Pawel Uchto","pt":"i","n":"Maro Transport (Nw) Limited","no":"09279089","t":"Manchester","i":"transport","in":"Road Transport & Haulage","r":"north-west","rn":"North West England"},{"pn":"Sharon Ucer","pt":"i","n":"Bz Conway Ltd","no":"SC723739","t":"Edinburgh","i":"transport","in":"Road Transport & Haulage","r":"scotland","rn":"Scotland"},{"pn":"Chukwuka Tochukwu Uchendu","pt":"i","n":"Chukschi Logistics Limited","no":"16537411","t":"Walsall","i":"transport","in":"Road Transport & Haulage","r":"west-midlands","rn":"West Midlands"},{"pn":"Mr. Mehmet Ucum","pt":"i","n":"Real Plastic Recycle Limited","no":"15710578","t":"London","i":"waste-management","in":"Waste Management & Recycling","r":"london","rn":"London"},{"pn":"Mr Dogan Ucar","pt":"i","n":"Europol Wholesale Limited","no":"11271966","t":"Peterborough","i":"wholesale","in":"Wholesale & Distribution","r":"east-midlands","rn":"East Midlands"},{"pn":"Mr Erhan Uckun","pt":"i","n":"Medicare Supply Limited","no":"12628475","t":"London","i":"wholesale","in":"Wholesale & Distribution","r":"london","rn":"London"},{"pn":"Ekrem Uc","pt":"i","n":"Gratuity Ltd","no":"15023408","t":"London","i":"wholesale","in":"Wholesale & Distribution","r":"london","rn":"London"},{"pn":"Mr Ufuk Ucar","pt":"i","n":"K2C International Trade Ltd","no":"14120196","t":"London","i":"wholesale","in":"Wholesale & Distribution","r":"london","rn":"London"},{"pn":"Mr Muhammed Cihad Ucar","pt":"i","n":"D-Trade London Ltd","no":"12214531","t":"London","i":"wholesale","in":"Wholesale & Distribution","r":"london","rn":"London"},{"pn":"Mr Dogan Ucar","pt":"i","n":"Advanced Design & Display Limited","no":"17033034","t":"London","i":"wholesale","in":"Wholesale & Distribution","r":"london","rn":"London"},{"pn":"Mr Aze Janberk Ucar","pt":"i","n":"Mans Dune Ltd","no":"15835956","t":"London","i":"wholesale","in":"Wholesale & Distribution","r":"london","rn":"London"},{"pn":"Ms Sevda Ucanlar","pt":"i","n":"Turquoise London Ltd","no":"11934643","t":"Waltham Abbey","i":"wholesale","in":"Wholesale & Distribution","r":"london","rn":"London"},{"pn":"Mr Umit Ucar","pt":"i","n":"Mexis International Ltd","no":"12298093","t":"London","i":"wholesale","in":"Wholesale & Distribution","r":"london","rn":"London"},{"pn":"Mr Victor Obioma Uchechukwu","pt":"i","n":"Multidollar Victor Limited","no":"12671990","t":"Bradford","i":"wholesale","in":"Wholesale & Distribution","r":"yorkshire","rn":"Yorkshire & Humber"},{"pn":"Mr Vincent Uchegbu","pt":"i","n":"Antyjo International Ltd","no":"12388995","t":"Rotherham","i":"wholesale","in":"Wholesale & Distribution","r":"yorkshire","rn":"Yorkshire & Humber"}]